Workbook

Sheet CONTROLE DE PROPOSTAS_2026
A1: QNTD. | B1: DT. ABERTURA | C1: Nº PROPOSTA | D1: CLIENTE | E1: TIPO | F1: LOCAL EXECUÇÃO | G1: DESCRIÇÃO DOS SERVIÇOS | H1: TÉCNICO | I1: DATA LIMITE | J1: DATA ENVIO | K1: PRAZO EXECUÇÃO | L1: VALOR (R$) | M1: MARGEM | N1: RECEITA DIÁRIA | O1: STATUS PROPOSTA | P1: DATA VENDA | Q1: PEDIDO UNO | R1: PREVISÃO DE INICIO | S1: STATUS PEDIDO | T1: PEDIDOS DE COMPRA
A2: 8 | B2: 45669 | C2: P-3674 | D2: Air Liquide | E2: CLIENTE FINAL | F2: Maua/SP | G2: Instalação de 02 Transformadores à seco - Air Liquide | H2: COMERCIAL | I2: 46034 | J2: 46036 | K2: 4 | L2: 49980 | M2: 0.22 | N2: =IFERROR(Tabela225[[#This Row],[VALOR (R$)]]/Tabela225[[#This Row],[PRAZO EXECUÇÃO]],0) -> 12495 | O2: PERDIDA
A3: 9 | B3: 45669 | C3: P-3675 | D3: WEG | E3: FABRICANTE | F3: Blumenau/SC | G3: Montagem Completa de 01 Transformador de 525KV - AXIA SUL | H3: COMERCIAL | I3: 46037 | J3: 45669 | K3: 20 | L3: 229900 | M3: 0.22 | N3: =IFERROR(Tabela225[[#This Row],[VALOR (R$)]]/Tabela225[[#This Row],[PRAZO EXECUÇÃO]],0) -> 11495 | O3: PERDIDA
A4: 10 | B4: 45669 | C4: P-3676 | D4: WEG | E4: FABRICANTE | F4: Além Paraíba/MG | G4: Montagem Completa de 01 Transformador de 138KV - AXIA SUDESTE | H4: COMERCIAL | I4: 46037 | J4: 46034 | K4: 10 | L4: 128000 | M4: 0.2 | N4: =IFERROR(Tabela225[[#This Row],[VALOR (R$)]]/Tabela225[[#This Row],[PRAZO EXECUÇÃO]],0) -> 12800 | O4: APROVADA | P4: 46042 | Q4: 19691 | T4: RECEBIDO
A5: 204 | B5: 45915 | C5: P-3450 | D5: Cargill | E5: CLIENTE FINAL | F5: Uberlândia/MG | G5: Manutenção Corretiva em 02 Transformadores de AT | H5: COMERCIAL | I5: 45916 | J5: 45916 | K5: 20 | L5: 223001.4 | M5: 0.2 | N5: =IFERROR(Tabela225[[#This Row],[VALOR (R$)]]/Tabela225[[#This Row],[PRAZO EXECUÇÃO]],0) -> 11150.07 | O5: APROVADA | P5: 46139 | T5: RECEBIDO
A6: 2025 | B6: 45960 | C6: P-3573 | D6: Cerradinho Bio | E6: FABRICANTE | F6: Maracaju/MS | G6: Tratamento de óleo mineral isolante em 01 transformador de MT | I6: 45960 | K6: 1 | L6: 32940 | M6: 0.26 | N6: =IFERROR(Tabela225[[#This Row],[VALOR (R$)]]/Tabela225[[#This Row],[PRAZO EXECUÇÃO]],0) -> 32940 | O6: APROVADA | P6: 46030 | Q6: 19543 | S6: CONCLUÍDO | T6: RECEBIDO
A7: 2025 | B7: 45964 | C7: P-3572 | D7: WEG | E7: FABRICANTE | F7: Ribeiro Gonçaslves/PI | G7: ASTEC - Diarias Adicional Desmontagem Ribeiro Gonçaves/PI | I7: 46055 | J7: 46055 | K7: 5 | L7: 11500 | M7: 0.2 | N7: =IFERROR(Tabela225[[#This Row],[VALOR (R$)]]/Tabela225[[#This Row],[PRAZO EXECUÇÃO]],0) -> 2300 | O7: APROVADA | P7: 46055 | Q7: - | S7: CONCLUÍDO | T7: RECEBIDO
A8: 2025 | B8: 45964 | C8: P-3578 | D8: Energy Substation | E8: CLIENTE FINAL | F8: Fazendo Rio Grande/PR | G8: Montagem Completa de 01 Transformador de 138KV + Fornecimento de óleo isolante | H8: COMERCIAL | I8: 45964 | K8: 9 | L8: 324200 | M8: 0.145 | N8: =IFERROR(Tabela225[[#This Row],[VALOR (R$)]]/Tabela225[[#This Row],[PRAZO EXECUÇÃO]],0) -> 36022.222 | O8: APROVADA | P8: 46035 | Q8: 19596 | S8: CONCLUÍDO | T8: RECEBIDO
A9: 2025 | B9: 45974 | C9: P-3575B | D9: TSEA | E9: FABRICANTE | F9: Montes Claros/MG | G9: Montagem Completa de 02 Transformadores de 138KV - NOVONORDISK | I9: 45974 | J9: 45974 | K9: 20 | L9: =134900*2 -> 269800 | M9: 0.21 | N9: =IFERROR(Tabela225[[#This Row],[VALOR (R$)]]/Tabela225[[#This Row],[PRAZO EXECUÇÃO]],0) -> 13490 | O9: APROVADA | P9: 46065 | Q9: 20021 | T9: RECEBIDO
A10: 2025 | B10: 45987 | C10: P-3627 | D10: CONSAG | E10: CLIENTE FINAL | F10: BARCARENA/PA | G10: Montagem Completa de 01 Transformador de 21KV - PORTOCEM | H10: COMERCIAL | I10: 45988 | K10: 14 | L10: 271800 | M10: 0.26 | N10: =IFERROR(Tabela225[[#This Row],[VALOR (R$)]]/Tabela225[[#This Row],[PRAZO EXECUÇÃO]],0) -> 19414.286 | O10: APROVADA | P10: 46043 | Q10: 19766 | T10: RECEBIDO
A11: 2025 | B11: 45987 | C11: P-3628 | D11: WEG | E11: FABRICANTE | F11: Manaus/AM | G11: ADITIVO - Locação de Equipamentos - ASTEC | H11: TÉCNICO | I11: 46055 | J11: 46055 | K11: 5 | L11: 10950 | M11: 0.2 | N11: =IFERROR(Tabela225[[#This Row],[VALOR (R$)]]/Tabela225[[#This Row],[PRAZO EXECUÇÃO]],0) -> 2190 | O11: APROVADA | P11: 46055 | Q11: - | S11: CONCLUÍDO | T11: RECEBIDO
A12: 2025 | B12: 46001 | C12: P-3625D | D12: CARGILL | E12: CLIENTE FINAL | F12: Uberlândia/MG | G12: Manutenção Corretiva em 01 Transformador de 13.8 KV - ETAPA2 | I12: 46051 | J12: 46051 | K12: 15 | L12: 50292.5 | M12: 0.2 | N12: =IFERROR(Tabela225[[#This Row],[VALOR (R$)]]/Tabela225[[#This Row],[PRAZO EXECUÇÃO]],0) -> 3352.8333 | O12: APROVADA | P12: 46051 | Q12: 19268 | S12: CONCLUÍDO | T12: RECEBIDO
A13: 2025 | B13: 46001 | C13: P-3647A | D13: WEG | E13: FABRICANTE | F13: Gravatai/RS | G13: ADITIVO - DIARIAS ADICIONAIS, FORNECIMENTO DE MÃO DE OBRA ADICIONAL E BOMBA DE VÁCUO ADICIONAL | H13: TÉCNICO | I13: 46001 | J13: 46001 | L13: 611630 | M13: 0.2 | N13: =IFERROR(Tabela225[[#This Row],[VALOR (R$)]]/Tabela225[[#This Row],[PRAZO EXECUÇÃO]],0) -> 0 | O13: APROVADA | P13: 46136 | T13: RECEBIDO
A14: 2025 | B14: 46007 | C14: P-3659 | D14: WEG | E14: FABRICANTE | F14: Manaus/AM | G14: ADITIVO - Montagem Completa de 138KV - CEA PROMON - Diarias Adicionais - ASTEC | H14: TÉCNICO | I14: 46055 | J14: 46055 | K14: 5 | L14: 72360 | M14: 0.2 | N14: 72360 | O14: APROVADA | P14: 46055 | Q14: - | T14: RECEBIDO
A15: 2025 | B15: 46020 | C15: P-3665 | D15: WEG | E15: FABRICANTE | F15: Serra/ES | G15: Manutenção Corretiva em 01 Transformador de AR - ArcerlorMittal - ASTEC | I15: 46055 | J15: 46055 | K15: 5 | L15: 50554 | M15: 0.2 | N15: =IFERROR(Tabela225[[#This Row],[VALOR (R$)]]/Tabela225[[#This Row],[PRAZO EXECUÇÃO]],0) -> 10110.8 | O15: APROVADA | P15: 46055 | Q15: - | T15: RECEBIDO
A16: 1 | B16: 46024 | C16: P-3667 | D16: CPFL TRANSMISSÃO | E16: CLIENTE FINAL | F16: - | G16: Recebimento, transporte, montagem, e comissionamento de 03 transformadores | H16: COMERCIAL | I16: 46045 | J16: 46063 | K16: 25 | L16: 11481503 | M16: - | N16: =IFERROR(Tabela225[[#This Row],[VALOR (R$)]]/Tabela225[[#This Row],[PRAZO EXECUÇÃO]],0) -> 459260.12 | O16: PERDIDA
A17: 2 | B17: 46027 | C17: P-3668 | D17: Suzano Papel e Celulose | E17: CLIENTE FINAL | F17: Três Lagoas/MS | G17: Manutenção Preventiva e Corretiva em Transformadores | H17: COMERCIAL | I17: 45662 | J17: 46027 | K17: 0 | L17: 300000 | M17: 0.2 | N17: =IFERROR(Tabela225[[#This Row],[VALOR (R$)]]/Tabela225[[#This Row],[PRAZO EXECUÇÃO]],0) -> 0 | O17: NEGOCIAÇÃO
A18: 3 | B18: 46027 | C18: P-3669 | D18: Petrobras | E18: CLIENTE FINAL | F18: Cubatão/SP | G18: Manutenção Corretiva de 02 Transformadores de AT | H18: COMERCIAL | I18: 46027 | J18: 46027 | K18: 26 | L18: =20634+35223+226400 -> 282257 | M18: 0.27 | N18: =IFERROR(Tabela225[[#This Row],[VALOR (R$)]]/Tabela225[[#This Row],[PRAZO EXECUÇÃO]],0) -> 10856.038 | O18: PERDIDA
A19: 4 | B19: 46028 | C19: P-3670 | D19: DATA | E19: FABRICANTE | F19: Cezarina/GO | G19: Montagem de 02 transformadores de AT - EQUATORIAL | H19: COMERCIAL | I19: 46028 | J19: 46028 | K19: 17 | L19: 157720 | M19: 0.24 | N19: =IFERROR(Tabela225[[#This Row],[VALOR (R$)]]/Tabela225[[#This Row],[PRAZO EXECUÇÃO]],0) -> 9277.6471 | O19: PERDIDA
A20: 5 | B20: 46030 | C20: P-3671 | D20: Sungrow | E20: CLIENTE FINAL | F20: Paracatu/MG | G20: Tratamento de Óleo Isolante Emergencial em 40 transformadores - ATLAS | H20: COMERCIAL | I20: 46030 | J20: 46030 | K20: 20 | L20: 535860 | M20: 0.23 | N20: =IFERROR(Tabela225[[#This Row],[VALOR (R$)]]/Tabela225[[#This Row],[PRAZO EXECUÇÃO]],0) -> 26793 | O20: APROVADA | P20: 46031 | Q20: 19573 | T20: RECEBIDO
A21: 6 | B21: 46030 | C21: P-3672 | D21: MR | E21: CLIENTE FINAL | F21: Charqueada/RS | G21: Fornecimento de Mão de Obra - CPFL | H21: COMERCIAL | I21: 46030 | J21: 45666 | K21: 10 | L21: =33800+29990 -> 63790 | M21: 0.25 | N21: =IFERROR(Tabela225[[#This Row],[VALOR (R$)]]/Tabela225[[#This Row],[PRAZO EXECUÇÃO]],0) -> 6379 | O21: PERDIDA
A22: 7 | B22: 46031 | C22: P-3673 | D22: CPFL | E22: CLIENTE FINAL | F22: Sabino/SP | G22: Enchimento de óleo em 01 transformador de 34,5KV | H22: COMERCIAL | I22: 45666 | J22: 45666 | K22: 3 | L22: 34200 | M22: 0.23 | N22: =IFERROR(Tabela225[[#This Row],[VALOR (R$)]]/Tabela225[[#This Row],[PRAZO EXECUÇÃO]],0) -> 11400 | O22: PERDIDA
A23: 11 | B23: 46035 | C23: P-8882.26 | D23: WEG | E23: FABRICANTE | F23: São Paulo/SP | G23: Montagem completa de 04 Transformadores de 230KV - CTEEP | H23: COMERCIAL | I23: 46038 | J23: 46035 | K23: 54 | L23: 919200 | M23: 0.24 | N23: =IFERROR(Tabela225[[#This Row],[VALOR (R$)]]/Tabela225[[#This Row],[PRAZO EXECUÇÃO]],0) -> 17022.222 | O23: PERDIDA
A24: 12 | B24: 46036 | C24: P-8888.26 | D24: CSN | E24: CLIENTE FINAL | F24: Arcos/MG | G24: Manutenção Corretiva de 05 Transformadores de MT - CSN Cimento | H24: COMERCIAL | I24: 46036 | N24: =IFERROR(Tabela225[[#This Row],[VALOR (R$)]]/Tabela225[[#This Row],[PRAZO EXECUÇÃO]],0) -> 0 | O24: CANCELADA
A25: 13 | B25: 46036 | C25: P-8893.26 | D25: WEG | E25: FABRICANTE | F25: Andradina/SP | G25: Montagem Completa de 03 transformadores de 440KV - CTEEP | H25: COMERCIAL | I25: 46038 | J25: 46038 | K25: =15*3 -> 45 | L25: 538800 | M25: 0.22 | N25: =IFERROR(Tabela225[[#This Row],[VALOR (R$)]]/Tabela225[[#This Row],[PRAZO EXECUÇÃO]],0) -> 11973.333 | O25: PERDIDA
A26: 14 | B26: 46036 | C26: P-8895.26 | D26: WEG | E26: FABRICANTE | F26: Olindina/BA | G26: Montagem Completa de 03 transformadores de 550KV - CHESF | H26: COMERCIAL | I26: 46041 | J26: 46038 | K26: =13*3 -> 39 | L26: 479700 | M26: 0.24 | N26: =IFERROR(Tabela225[[#This Row],[VALOR (R$)]]/Tabela225[[#This Row],[PRAZO EXECUÇÃO]],0) -> 12300 | O26: PERDIDA
A27: 15 | B27: 46036 | C27: P-8897.26 | D27: Montecalm | E27: FABRICANTE | F27: Pindamonhagaba/SP | G27: Drenagem de óleo Mineral - Gerdau | H27: COMERCIAL | I27: 46036 | J27: 46036 | K27: 2 | L27: 245985 | M27: 0.23 | N27: =IFERROR(Tabela225[[#This Row],[VALOR (R$)]]/Tabela225[[#This Row],[PRAZO EXECUÇÃO]],0) -> 122992.5 | O27: PERDIDA
A28: 16 | B28: 46036 | C28: P-8899.26 | D28: WEG | E28: FABRICANTE | F28: Barcarena/PA | G28: (Maquina 03) Montagem Completa de 01 transformador de 550KV - Portocem | H28: COMERCIAL | I28: 46041 | J28: 46036 | K28: 35 | L28: 310000 | M28: 0.205 | N28: =IFERROR(Tabela225[[#This Row],[VALOR (R$)]]/Tabela225[[#This Row],[PRAZO EXECUÇÃO]],0) -> 8857.1429 | O28: APROVADA | P28: 46062 | T28: RECEBIDO
A29: 17 | B29: 46036 | C29: P-8899.26 | D29: WEG | E29: FABRICANTE | F29: Barcarena/PA | G29: (Maquina 03) Mão de Obra Adicional - PORTOCEM | H29: 46041 | I29: 46036 | J29: 46036 | K29: 35 | L29: 103250 | M29: 0.205 | N29: =IFERROR(Tabela225[[#This Row],[VALOR (R$)]]/Tabela225[[#This Row],[PRAZO EXECUÇÃO]],0) -> 2950 | O29: APROVADA | P29: 46062 | T29: RECEBIDO
A30: 18 | B30: 46036 | C30: P-8902.26 | D30: CELEO | E30: FABRICANTE | F30: São João do Piaui/PI | G30: ADITIVO - Manutenção Corretiva em Transformadores de 36,2kv - CELEO | H30: TÉCNICO | I30: 46037 | J30: 46036 | K30: 2 | L30: 77544.88 | M30: 0.25 | N30: =IFERROR(Tabela225[[#This Row],[VALOR (R$)]]/Tabela225[[#This Row],[PRAZO EXECUÇÃO]],0) -> 38772.44 | O30: APROVADA | P30: 46073 | T30: RECEBIDO
A31: 19 | B31: 46036 | C31: P-8904.26 | D31: Air Liquide | E31: CLIENTE FINAL | F31: Maua/SP | G31: Manutenção preventiva Eletrocentro - AIR LIQUIDE | H31: COMERCIAL | I31: 46036 | J31: 46036 | K31: 1 | L31: 69940 | M31: 0.22 | N31: =IFERROR(Tabela225[[#This Row],[VALOR (R$)]]/Tabela225[[#This Row],[PRAZO EXECUÇÃO]],0) -> 69940 | O31: PERDIDA
A32: 20 | B32: 46036 | C32: P-8905.26 | D32: Air Liquide | E32: CLIENTE FINAL | F32: Maua/SP | G32: Aquisição de 02 transformadores - AIR LIQUIDE | H32: COMERCIAL | I32: 46036 | J32: 46036 | K32: 1 | L32: 36000 | M32: 0.23 | N32: =IFERROR(Tabela225[[#This Row],[VALOR (R$)]]/Tabela225[[#This Row],[PRAZO EXECUÇÃO]],0) -> 36000 | O32: PERDIDA
A33: 2025 | B33: 46037 | C33: P-3648A | D33: WEG | E33: FABRICANTE | F33: Jaboatão dos Guararapes/PE | G33: Aditivo de Diarias adicionais e Mob/Desmob - PROJETO 129 | H33: TÉCNICO | I33: 46052 | J33: 46052 | K33: 1 | L33: 184000 | M33: 0.2 | N33: =IFERROR(Tabela225[[#This Row],[VALOR (R$)]]/Tabela225[[#This Row],[PRAZO EXECUÇÃO]],0) -> 184000 | O33: APROVADA | P33: 46052 | Q33: - | S33: CONCLUÍDO | T33: RECEBIDO
A34: 21 | B34: 46037 | C34: P-8910.26 | D34: CPFL | E34: CLIENTE FINAL | F34: Marilia/SP | G34: Enchimento de óleo em 01 transformador de 138KV - CPFL | H34: COMERCIAL | I34: 46037 | J34: 46037 | K34: 3 | L34: 34940 | M34: 0.22 | N34: =IFERROR(Tabela225[[#This Row],[VALOR (R$)]]/Tabela225[[#This Row],[PRAZO EXECUÇÃO]],0) -> 11646.667 | O34: PERDIDA
A35: 22 | B35: 46037 | C35: P-8912.26 | D35: ALUPAR | E35: FABRICANTE | F35: Varzea Grande/MT | G35: Manutenção corretiva em 01 transformador de 230KV - TRANSMISSÃO DE VARZEA | H35: COMERCIAL | I35: 46037 | J35: 46037 | K35: 15 | L35: 319960.1 | M35: 0.22 | N35: =IFERROR(Tabela225[[#This Row],[VALOR (R$)]]/Tabela225[[#This Row],[PRAZO EXECUÇÃO]],0) -> 21330.673 | O35: EM ABERTO
A36: 23 | B36: 46038 | C36: P-8917.26 | D36: TSEA | E36: FABRICANTE | F36: Eldorado do Sul/RS | G36: Montagem Completa de 01 Reator de 525KV - ELETROSUL | H36: COMERCIAL | I36: 46038 | J36: 46038 | K36: 12 | L36: 228643.51 | M36: 0.21 | N36: =IFERROR(Tabela225[[#This Row],[VALOR (R$)]]/Tabela225[[#This Row],[PRAZO EXECUÇÃO]],0) -> 19053.626 | O36: PERDIDA
A37: 24 | B37: 46038 | C37: P-8918.26 | D37: CYMI | E37: CLIENTE FINAL | F37: Estreito/MG | G37: Manutenção Corretiva em 01 Reator de 500KV | H37: COMERCIAL | I37: 46038 | J37: 46038 | K37: 6 | L37: 199925 | M37: 0.2 | N37: =IFERROR(Tabela225[[#This Row],[VALOR (R$)]]/Tabela225[[#This Row],[PRAZO EXECUÇÃO]],0) -> 33320.833 | O37: APROVADA | P37: 46043 | Q37: 19698 | S37: CONCLUÍDO | T37: RECEBIDO
A38: 25 | B38: 46038 | C38: P-8920.26 | D38: WEG | E38: FABRICANTE | F38: Santa Luzia/PB | G38: Montagem Completa de 01 Reator de 500KV - NEOENERGIA | H38: COMERCIAL | I38: 46041 | J38: 46041 | K38: 13 | L38: 224280 | M38: 0.24 | N38: =IFERROR(Tabela225[[#This Row],[VALOR (R$)]]/Tabela225[[#This Row],[PRAZO EXECUÇÃO]],0) -> 17252.308 | O38: PERDIDA
A39: 26 | B39: 46041 | C39: P-8927.26 | D39: WEG | E39: FABRICANTE | F39: Marabá/PA | G39: Manutenção Corretiva em 01 Transformador de 69KV - ELETRONORTE | H39: COMERCIAL | I39: 46045 | J39: 46045 | K39: 1 | L39: 45490 | M39: 0.24 | N39: =IFERROR(Tabela225[[#This Row],[VALOR (R$)]]/Tabela225[[#This Row],[PRAZO EXECUÇÃO]],0) -> 45490 | O39: PERDIDA
A40: 27 | B40: 46043 | C40: P-8942.26 | D40: WEG | E40: FABRICANTE | F40: Curvelo/MG | G40: Manutenção Corretiva em 01 transformador de 13,8KV - CEMIG/VISION | H40: COMERCIAL | I40: 46052 | J40: 46052 | K40: 5 | L40: 119200 | M40: 0.23 | N40: =IFERROR(Tabela225[[#This Row],[VALOR (R$)]]/Tabela225[[#This Row],[PRAZO EXECUÇÃO]],0) -> 23840 | O40: PERDIDA
A41: 28 | B41: 46044 | C41: P-8946.26 | D41: WEG | E41: FABRICANTE | F41: Turmalina/MG | G41: Manutenção Corretiva em 01 transformador de 13,8 KV - CEMIG | H41: COMERCIAL | I41: 46050 | J41: 46044 | K41: 2 | L41: 49900 | M41: 0.24 | N41: =IFERROR(Tabela225[[#This Row],[VALOR (R$)]]/Tabela225[[#This Row],[PRAZO EXECUÇÃO]],0) -> 24950 | O41: PERDIDA
A42: 29 | B42: 46044 | C42: P-8951.26 | D42: Sungrow | E42: CLIENTE FINAL | F42: Paracatu/MG | G42: Locação de Equipamento para Analise Dieletrica - ATLAS | H42: COMERCIAL | I42: 46044 | J42: 46044 | K42: 1 | L42: 15000 | M42: 0.22 | N42: =IFERROR(Tabela225[[#This Row],[VALOR (R$)]]/Tabela225[[#This Row],[PRAZO EXECUÇÃO]],0) -> 15000 | O42: PERDIDA
A43: 30 | B43: 46044 | C43: P-8954.26 | D43: Tereme | E43: CLIENTE FINAL | F43: Pindamonhagaba/SP | G43: Desmontagem Completa de 01 Transformador de 23KV - GERDAU | H43: COMERCIAL | I43: 46044 | J43: 46044 | K43: 7 | L43: =27430.2+39190.2+7350+10290+4410 -> 88670.4 | M43: 0.2 | N43: =IFERROR(Tabela225[[#This Row],[VALOR (R$)]]/Tabela225[[#This Row],[PRAZO EXECUÇÃO]],0) -> 12667.2 | O43: APROVADA | P43: 46050 | Q43: 19825 | S43: CONCLUÍDO | T43: RECEBIDO
A44: 31 | B44: 46048 | C44: P-8960.26 | D44: WEG | E44: FABRICANTE | F44: Palhoça/SC | G44: Montagem Completa de 01 transformador de 138KV - CELESC | H44: COMERCIAL | I44: 46050 | J44: 28/01/20260 | K44: 10 | L44: 163200 | M44: 0.23 | N44: =IFERROR(Tabela225[[#This Row],[VALOR (R$)]]/Tabela225[[#This Row],[PRAZO EXECUÇÃO]],0) -> 16320 | O44: PERDIDA
A45: 32 | B45: 46048 | C45: P-8970.26 | D45: WEG | E45: FABRICANTE | F45: Aparecida de Goiania/GO | G45: Manutenção Corretiva em 01 transformador de 230KV - FURNAS | H45: COMERCIAL | I45: 46052 | J45: 46050 | K45: 7 | L45: 120990 | M45: 0.23 | N45: =IFERROR(Tabela225[[#This Row],[VALOR (R$)]]/Tabela225[[#This Row],[PRAZO EXECUÇÃO]],0) -> 17284.286 | O45: PERDIDA
A46: 33 | B46: 46048 | C46: P-8971.26 | D46: WEG | E46: FABRICANTE | F46: Paraíso das Aguas/MS | G46: Desmontagem, Montagem e comissionamento de 01 Reator de 230KV - NEOENERGIA | H46: COMERCIAL | I46: 46051 | J46: 46051 | K46: 15 | L46: 232700 | M46: 0.23 | N46: =IFERROR(Tabela225[[#This Row],[VALOR (R$)]]/Tabela225[[#This Row],[PRAZO EXECUÇÃO]],0) -> 15513.333 | O46: PERDIDA
A47: 34 | B47: 46049 | C47: P-8977.26 | D47: WEG | E47: FABRICANTE | F47: Pirituba/SP | G47: Montagem Completa de 01 Transformador de 220KV - CTEEP | H47: COMERCIAL | I47: 46051 | J47: 46049 | K47: 10 | L47: 123380 | M47: 0.22 | N47: =IFERROR(Tabela225[[#This Row],[VALOR (R$)]]/Tabela225[[#This Row],[PRAZO EXECUÇÃO]],0) -> 12338 | O47: PERDIDA
A48: 35 | B48: 46049 | C48: P-8980.26 | D48: CYMI | E48: CLIENTE FINAL | F48: Linhares/ES | G48: Manutenção Corretiva em 01 transformador de 13,8KV - CEMIG/VISION+Aditivo Óleo | H48: TÉCNICO | I48: 46049 | J48: 46049 | K48: 1 | L48: =14487+6000 -> 20487 | M48: 0.2 | N48: =IFERROR(Tabela225[[#This Row],[VALOR (R$)]]/Tabela225[[#This Row],[PRAZO EXECUÇÃO]],0) -> 20487 | O48: APROVADA | P48: 46065 | Q48: 19698 | T48: RECEBIDO
A49: 36 | B49: 46049 | C49: P-8984.26 | D49: WEG | E49: FABRICANTE | F49: Ubaí/MG | G49: Montagem Completa de 01 transformador de 138KV - CEMIG | H49: COMERCIAL | I49: 46049 | J49: 46049 | K49: 8 | L49: 168900 | M49: 0.21 | N49: =IFERROR(Tabela225[[#This Row],[VALOR (R$)]]/Tabela225[[#This Row],[PRAZO EXECUÇÃO]],0) -> 21112.5 | O49: PERDIDA
A50: 37 | B50: 46049 | C50: P-8985.26 | D50: WEG | E50: FABRICANTE | F50: São Desiderio/BA | G50: Montagem Completa de 03 transformadores de 230KV - TAESA | H50: COMERCIAL | I50: 46055 | J50: 46055 | K50: =12*3 -> 36 | L50: 517740 | M50: 0.22 | N50: =IFERROR(Tabela225[[#This Row],[VALOR (R$)]]/Tabela225[[#This Row],[PRAZO EXECUÇÃO]],0) -> 14381.667 | O50: PERDIDA
A51: 38 | B51: 46050 | C51: P-9002.26 | D51: JR FEYH | E51: CLIENTE FINAL | F51: SP-MG-GO | G51: Montagem Completa de 42 Reator de 500KV | H51: COMERCIAL | I51: 46050 | J51: 46050 | K51: =98+294+196 -> 588 | L51: =2042600+3063900+1021300 -> 6127800 | M51: 0.26 | N51: =IFERROR(Tabela225[[#This Row],[VALOR (R$)]]/Tabela225[[#This Row],[PRAZO EXECUÇÃO]],0) -> 10421.429 | O51: PERDIDA
A52: 39 | B52: 46050 | C52: P-9004.26 | D52: WEG | E52: FABRICANTE | F52: Maceio/AL | G52: Aditivo de Diarias adicionais Projeto-195 | H52: TÉCNICO | I52: 46051 | J52: 46051 | K52: 1 | L52: 49600 | M52: 0.2 | N52: =IFERROR(Tabela225[[#This Row],[VALOR (R$)]]/Tabela225[[#This Row],[PRAZO EXECUÇÃO]],0) -> 49600 | O52: APROVADA | P52: 46118 | S52: CONCLUÍDO | T52: RECEBIDO
A53: 40 | B53: 46051 | C53: P-9010.26 | D53: Tereme | E53: CLIENTE FINAL | F53: São João da Barra/RJ | G53: Manutenção Corretiva de 02 transformadores | H53: COMERCIAL | I53: 46051 | J53: 46051 | K53: 3 | L53: =16500+23800 -> 40300 | M53: 0.25 | N53: =IFERROR(Tabela225[[#This Row],[VALOR (R$)]]/Tabela225[[#This Row],[PRAZO EXECUÇÃO]],0) -> 13433.333 | O53: PERDIDA
A54: 41 | B54: 46051 | C54: P-9017.26 | D54: WEG | E54: FABRICANTE | F54: Rorainopolis/RR | G54: Manutenção Corretiva de 01 reator de 550KV - TRANSNORTE | H54: COMERCIAL | I54: 46055 | J54: 46055 | K54: 2 | L54: 220600 | M54: 0.28 | N54: =IFERROR(Tabela225[[#This Row],[VALOR (R$)]]/Tabela225[[#This Row],[PRAZO EXECUÇÃO]],0) -> 110300 | O54: PERDIDA
A55: 42 | B55: 46052 | C55: P-9019.26 | D55: WEG | E55: FABRICANTE | F55: Vila Propicio/GO | G55: Manutenção Corretiva de 01 transformador de 230KV - HITACHI | H55: COMERCIAL | I55: 46055 | J55: 46055 | K55: 2 | L55: 44200 | M55: 0.25 | N55: =IFERROR(Tabela225[[#This Row],[VALOR (R$)]]/Tabela225[[#This Row],[PRAZO EXECUÇÃO]],0) -> 22100 | O55: PERDIDA
A56: 43 | B56: 46052 | C56: P-9020.26 | D56: CHINT | E56: FABRICANTE | F56: Ferreiras Gomes/AP | G56: Montagem Completa de 01 transformador de 230KV - ELETROBRAS | H56: COMERCIAL | I56: 46086 | J56: 46058 | K56: 18 | L56: 406162 | M56: 0.23 | N56: =IFERROR(Tabela225[[#This Row],[VALOR (R$)]]/Tabela225[[#This Row],[PRAZO EXECUÇÃO]],0) -> 22564.556 | O56: EM ABERTO
A57: 44 | B57: 46052 | C57: P-9021.26 | D57: COX | E57: FABRICANTE | F57: São João do Piaui/PI | G57: Desmontagem, Transporte e Montagem de 06 Reatores de AT | H57: COMERCIAL | I57: 46055 | J57: 46055 | K57: 48 | L57: 735540 | M57: 0.25 | N57: =IFERROR(Tabela225[[#This Row],[VALOR (R$)]]/Tabela225[[#This Row],[PRAZO EXECUÇÃO]],0) -> 15323.75 | O57: PERDIDA
A58: 45 | B58: 46052 | C58: P-9024.26 | D58: JMX ENERGY | E58: FABRICANTE | F58: Cordovil-RJ | G58: Desmontagem e montagem completa de 02 transformadores de 138KV - SETD LIGHT | H58: COMERCIAL | I58: 46056 | N58: =IFERROR(Tabela225[[#This Row],[VALOR (R$)]]/Tabela225[[#This Row],[PRAZO EXECUÇÃO]],0) -> 0 | O58: CANCELADA
A59: 46 | B59: 46055 | C59: P-9029.26 | D59: WEG | E59: FABRICANTE | F59: Blumenau/SC | G59: Coletas e Ensaios eletricos - AXIA ENERGIA | H59: COMERCIAL | I59: 46055 | N59: =IFERROR(Tabela225[[#This Row],[VALOR (R$)]]/Tabela225[[#This Row],[PRAZO EXECUÇÃO]],0) -> 0 | O59: CANCELADA
A60: 47 | B60: 46056 | C60: P-9033.26 | D60: WEG | E60: FABRICANTE | F60: Imperatriz/PI | G60: Aditivo - Manutenção Corretiva de 01 reator | H60: TÉCNICO | I60: 46056 | J60: 46056 | K60: 1 | L60: 14400 | M60: 0.26 | N60: =IFERROR(Tabela225[[#This Row],[VALOR (R$)]]/Tabela225[[#This Row],[PRAZO EXECUÇÃO]],0) -> 14400 | O60: APROVADA | P60: 46066 | S60: CONCLUÍDO | T60: RECEBIDO
A61: 58 | B61: 46056 | C61: P-9064.26 | D61: WEG | E61: FABRICANTE | F61: Cachoeira de Minas/MG | G61: Montagem Completa de 01 transformador de 138KV - CEMIG | H61: COMERCIAL | I61: 46059 | J61: 46056 | K61: 7 | L61: 100000 | M61: 0.21 | N61: =IFERROR(Tabela225[[#This Row],[VALOR (R$)]]/Tabela225[[#This Row],[PRAZO EXECUÇÃO]],0) -> 14285.714 | O61: APROVADA | P61: 46063 | Q61: 19986 | T61: RECEBIDO
A62: 48 | B62: 46057 | C62: P-9040.26 | D62: WEG | E62: FABRICANTE | F62: Santo Andre/SP | G62: Manutenção Corretiva em 01 transformador de 440Kv - UNIPAR | H62: COMERCIAL | I62: 46057 | J62: 46057 | K62: 6 | L62: 120000 | M62: 0.24 | N62: =IFERROR(Tabela225[[#This Row],[VALOR (R$)]]/Tabela225[[#This Row],[PRAZO EXECUÇÃO]],0) -> 20000 | O62: PERDIDA
A63: 49 | B63: 46057 | C63: P-9046.26 | D63: CELEO | E63: CLIENTE FINAL | F63: Nova Ponte/MG | G63: Manutenção Corretiva de 03 reatores de 500KV - CELEO | H63: COMERCIAL | I63: 46058 | J63: 46058 | K63: 39 | L63: 449900 | M63: 0.26 | N63: =IFERROR(Tabela225[[#This Row],[VALOR (R$)]]/Tabela225[[#This Row],[PRAZO EXECUÇÃO]],0) -> 11535.897 | O63: EM ABERTO
A64: 50 | B64: 46058 | C64: P-9051.26 | D64: WEG | E64: FABRICANTE | F64: Nova Era/MG | G64: Montagem Completa de 01 transformador de forno de 138KV - SILICON | H64: COMERCIAL | I64: 46059 | J64: 46058 | K64: 10 | L64: 114900 | M64: 0.22 | N64: =IFERROR(Tabela225[[#This Row],[VALOR (R$)]]/Tabela225[[#This Row],[PRAZO EXECUÇÃO]],0) -> 11490 | O64: APROVADA | P64: 46062 | Q64: 19948 | T64: RECEBIDO
A65: 51 | B65: 46058 | C65: P-9053.26 | D65: WEG | E65: FABRICANTE | F65: Milagres/CE | G65: Montagem Completa de 01 Reator de 500KV - NEOENERGIA | H65: COMERCIAL | I65: 46062 | J65: 46058 | K65: 12 | L65: 233800 | M65: 0.21 | N65: =IFERROR(Tabela225[[#This Row],[VALOR (R$)]]/Tabela225[[#This Row],[PRAZO EXECUÇÃO]],0) -> 19483.333 | O65: PERDIDA
A66: 52 | B66: 46058 | C66: P-9054.26 | D66: WEG | E66: FABRICANTE | F66: Pirajuba/MG | G66: Montagem Completa de 01 transformador de 138KV - USINA SANTO ANGELO | H66: COMERCIAL | I66: 46062 | J66: 46058 | K66: 7 | L66: 135000 | M66: 0.21 | N66: =IFERROR(Tabela225[[#This Row],[VALOR (R$)]]/Tabela225[[#This Row],[PRAZO EXECUÇÃO]],0) -> 19285.714 | O66: APROVADA | P66: 46099 | Q66: 20371 | T66: RECEBIDO
A67: 53 | B67: 46058 | C67: P-9055.26 | D67: WEG | E67: FABRICANTE | F67: Angelim/PE | G67: Montagem Completa de 03 Reatores de 550KV - CNS/CHESF | H67: COMERCIAL | I67: 46064 | J67: 46178 | K67: 42 | L67: =184900*3 -> 554700 | M67: 0.22 | N67: =IFERROR(Tabela225[[#This Row],[VALOR (R$)]]/Tabela225[[#This Row],[PRAZO EXECUÇÃO]],0) -> 13207.143 | O67: PERDIDA
A68: 54 | B68: 46058 | C68: P-9056.26 | D68: WEG | E68: FABRICANTE | F68: Resende/RJ | G68: Montagem Completa de 04 reatores de 550KV - AXIA | H68: COMERCIAL | I68: 46065 | J68: 46178 | K68: =14*4 -> 56 | L68: =155900*4 -> 623600 | M68: 0.22 | N68: =IFERROR(Tabela225[[#This Row],[VALOR (R$)]]/Tabela225[[#This Row],[PRAZO EXECUÇÃO]],0) -> 11135.714 | O68: PERDIDA
A69: 56 | B69: 46059 | C69: P-9059.26 | D69: CEBRACE | E69: CLIENTE FINAL | F69: Caçapava/SP | G69: Coleta e Analise de óleo - CEBRACE | H69: COMERCIAL | I69: 46065 | J69: 46059 | K69: 1 | L69: =4464+4212+4914 -> 13590 | M69: 0.22 | N69: =IFERROR(Tabela225[[#This Row],[VALOR (R$)]]/Tabela225[[#This Row],[PRAZO EXECUÇÃO]],0) -> 13590 | O69: PERDIDA
A70: 57 | B70: 46059 | C70: P-9062.26 | D70: Air Liquide | E70: CLIENTE FINAL | F70: São Jose dos Campos/SP | G70: Manutenção em sistemas eletricos de transformadores | H70: COMERCIAL | I70: 46065 | J70: 46059 | K70: 2 | L70: 66240 | M70: 0.25 | N70: =IFERROR(Tabela225[[#This Row],[VALOR (R$)]]/Tabela225[[#This Row],[PRAZO EXECUÇÃO]],0) -> 33120 | O70: PERDIDA
A71: 59 | B71: 46059 | C71: P-9064.26 | D71: WEG | E71: FABRICANTE | F71: Campanha/MG | G71: Montagem Completa de 01 transformador trifasico de 138kv - CEMIG | H71: COMERCIAL | I71: 46062 | J71: 46062 | K71: 7 | L71: 100000 | M71: 0.21 | N71: =IFERROR(Tabela225[[#This Row],[VALOR (R$)]]/Tabela225[[#This Row],[PRAZO EXECUÇÃO]],0) -> 14285.714 | O71: APROVADA | P71: 46063 | Q71: 19986 | T71: RECEBIDO
A72: 60 | B72: 46059 | C72: P-9064.26 | D72: WEG | E72: FABRICANTE | F72: Rio Acima/MG | G72: Montagem Completa de 01 transformador trifasico de 138kv - CEMIG | H72: COMERCIAL | I72: 46062 | J72: 46062 | K72: 7 | L72: 100000 | M72: 0.21 | N72: =IFERROR(Tabela225[[#This Row],[VALOR (R$)]]/Tabela225[[#This Row],[PRAZO EXECUÇÃO]],0) -> 14285.714 | O72: APROVADA | P72: 46063 | Q72: 19986 | T72: RECEBIDO
A73: 61 | B73: 46059 | C73: P-9066.26 | D73: WEG | E73: FABRICANTE | F73: Barcarena/PA | G73: Aditivo - Diarias adicionais maquinas 1 e 2 - PORTOCEM | H73: TÉCNICO | I73: 46062 | J73: 46062 | K73: 1 | L73: 430000 | M73: - | N73: =IFERROR(Tabela225[[#This Row],[VALOR (R$)]]/Tabela225[[#This Row],[PRAZO EXECUÇÃO]],0) -> 430000 | O73: APROVADA | P73: 46237 | T73: RECEBIDO
A74: 55 | B74: 46062 | C74: P-9058.26 | D74: Suzano Papel & Celulose | E74: CLIENTE FINAL | F74: Mucuri/BA | G74: Manutenção Corretiva em transformadores - SUZANO PAPEL & CELULOSE | H74: COMERCIAL | I74: 46065 | N74: =IFERROR(Tabela225[[#This Row],[VALOR (R$)]]/Tabela225[[#This Row],[PRAZO EXECUÇÃO]],0) -> 0 | O74: PERDIDA
A75: 62 | B75: 46062 | C75: P-9068.26 | D75: WEG | E75: FABRICANTE | F75: Luziania/GO | G75: Montagem Completa de 01 transformador trifasico de 138KV - EQUATORIAL | H75: COMERCIAL | I75: 46062 | J75: 46062 | K75: 7 | L75: 100000 | M75: 0.2 | N75: =IFERROR(Tabela225[[#This Row],[VALOR (R$)]]/Tabela225[[#This Row],[PRAZO EXECUÇÃO]],0) -> 14285.714 | O75: APROVADA | P75: 46066 | Q75: 20034 | T75: RECEBIDO
A76: 63 | B76: 46062 | C76: P-9069.26 | D76: WEG | E76: FABRICANTE | F76: Neripolis/GO | G76: Montagem Completa de 01 transformador trifasico de 69KV - EQUATORIAL | H76: COMERCIAL | I76: 46062 | J76: 46062 | K76: 7 | L76: 100000 | M76: 0.2 | N76: =IFERROR(Tabela225[[#This Row],[VALOR (R$)]]/Tabela225[[#This Row],[PRAZO EXECUÇÃO]],0) -> 14285.714 | O76: APROVADA | P76: 46066 | Q76: 20034 | T76: RECEBIDO
A77: 64 | B77: 46062 | C77: P-9073.26 | D77: WEG | E77: FABRICANTE | F77: Edeia/GO | G77: Montagem Completa de 01 transformador trifasico de 69KV - EQUATORIAL | H77: COMERCIAL | I77: 46062 | J77: 46062 | K77: 6 | L77: 100000 | M77: 0.2 | N77: =IFERROR(Tabela225[[#This Row],[VALOR (R$)]]/Tabela225[[#This Row],[PRAZO EXECUÇÃO]],0) -> 16666.667 | O77: APROVADA | P77: 46066 | Q77: 20034 | T77: RECEBIDO
A78: 65 | B78: 46062 | C78: P-9080.26 | D78: WEG | E78: FABRICANTE | F78: Paraiso das Aguas/MS | G78: Desmontagem e montagem completa de 02 transformadores de 138KV - NEOENERGIA | H78: COMERCIAL | I78: 46065 | N78: =IFERROR(Tabela225[[#This Row],[VALOR (R$)]]/Tabela225[[#This Row],[PRAZO EXECUÇÃO]],0) -> 0 | O78: PERDIDA
A79: 66 | B79: 46063 | C79: P-9083.26 | D79: ENGIE | E79: CLIENTE FINAL | F79: Piratuba/SC | G79: Manutenção Corretiva de transformador de AT - USH MACHADINHO | H79: COMERCIAL | I79: 46065 | J79: 46065 | K79: 2 | L79: 132900 | M79: 0.22 | N79: =IFERROR(Tabela225[[#This Row],[VALOR (R$)]]/Tabela225[[#This Row],[PRAZO EXECUÇÃO]],0) -> 66450 | O79: PERDIDA
A80: 67 | B80: 46064 | C80: P-9090.26 | D80: WEG | E80: FABRICANTE | F80: Itaberaí/GO | G80: Montagem Completa de 01 transformador de 138KV - EQUATORIAL | H80: COMERCIAL | I80: 46064 | J80: 46064 | K80: 7 | L80: 139900 | M80: 0.2 | N80: =IFERROR(Tabela225[[#This Row],[VALOR (R$)]]/Tabela225[[#This Row],[PRAZO EXECUÇÃO]],0) -> 19985.714 | O80: PERDIDA
A81: 68 | B81: 46064 | C81: P-9098.26 | D81: WEG | E81: FABRICANTE | F81: Janaúba/MG | G81: Inspeção - Manuntenção Corretiva em transormador de 550KV - ELERA | H81: COMERCIAL | I81: 46064 | J81: 46064 | K81: 5 | L81: 118140 | M81: 0.25 | N81: =IFERROR(Tabela225[[#This Row],[VALOR (R$)]]/Tabela225[[#This Row],[PRAZO EXECUÇÃO]],0) -> 23628 | O81: APROVADA | P81: 46066 | Q81: 20040 | T81: RECEBIDO
A82: 69 | B82: 46065 | C82: P-9108.26 | D82: WEG | E82: FABRICANTE | F82: Vargem Bonita/SC | G82: Montagem Completa de 01 transformador de 23.1KV - IRANI PAPEL | H82: COMERCIAL | I82: 46065 | J82: 46065 | K82: 5 | L82: 89900 | M82: 0.22 | N82: =IFERROR(Tabela225[[#This Row],[VALOR (R$)]]/Tabela225[[#This Row],[PRAZO EXECUÇÃO]],0) -> 17980 | O82: PERDIDA
A83: 70 | B83: 46065 | C83: P-9111.26 | D83: WEG | E83: FABRICANTE | F83: São Joaquim de Bicas/MG | G83: Montagem Completa de 01 transformador de 23.1KV - CEMIG | H83: COMERCIAL | I83: 46069 | J83: 46065 | K83: 14 | L83: 219800 | M83: 0.22 | N83: =IFERROR(Tabela225[[#This Row],[VALOR (R$)]]/Tabela225[[#This Row],[PRAZO EXECUÇÃO]],0) -> 15700 | O83: PERDIDA
A84: 73 | B84: 46066 | C84: P-9118.26 | D84: WEG | E84: FABRICANTE | F84: Rio Negrinho/SC | G84: Montagem Completa de 01 transformador de 138KV - CELESC | H84: COMERCIAL | I84: 46069 | J84: 46066 | K84: 10 | L84: 139900 | M84: 0.24 | N84: =IFERROR(Tabela225[[#This Row],[VALOR (R$)]]/Tabela225[[#This Row],[PRAZO EXECUÇÃO]],0) -> 13990 | O84: PERDIDA
A85: 75 | B85: 46071 | C85: P-9141.26 | D85: WEG | E85: FABRICANTE | F85: Pimenta Bueno/RO | G85: Montagem Completa de 01 transformador de 230KV - AXIA NORTE | H85: COMERCIAL | I85: 46073 | J85: 46072 | K85: 18 | L85: 413200 | M85: 0.23 | N85: =IFERROR(Tabela225[[#This Row],[VALOR (R$)]]/Tabela225[[#This Row],[PRAZO EXECUÇÃO]],0) -> 22955.556 | O85: PERDIDA
A86: 76 | B86: 46071 | C86: P-9142.26 | D86: WEG | E86: FABRICANTE | F86: Londrina/PR | G86: Montagem Completa de 01 transformador de 230KV - COPEL | H86: COMERCIAL | I86: 46073 | J86: 46072 | K86: 18 | L86: 239900 | M86: 0.22 | N86: =IFERROR(Tabela225[[#This Row],[VALOR (R$)]]/Tabela225[[#This Row],[PRAZO EXECUÇÃO]],0) -> 13327.778 | O86: PERDIDA
A87: 77 | B87: 46071 | C87: P-9143.26 | D87: WEG | E87: FABRICANTE | F87: Biguaçu/SC | G87: Montagem Completa de 01 transformador de 138KV - CEREJ | H87: COMERCIAL | I87: 46073 | J87: 46072 | K87: 10 | L87: 152064.7 | M87: 0.24 | N87: =IFERROR(Tabela225[[#This Row],[VALOR (R$)]]/Tabela225[[#This Row],[PRAZO EXECUÇÃO]],0) -> 15206.47 | O87: PERDIDA
A88: 78 | B88: 46071 | C88: P-9144.26 | D88: WEG | E88: FABRICANTE | F88: Jacinto Machado/SC | G88: Montagem Completa de 01 transformador de 138KV - CEJAMA | H88: COMERCIAL | I88: 46073 | J88: 46072 | K88: 7 | L88: 142270 | M88: 0.23 | N88: =IFERROR(Tabela225[[#This Row],[VALOR (R$)]]/Tabela225[[#This Row],[PRAZO EXECUÇÃO]],0) -> 20324.286 | O88: PERDIDA
A89: 79 | B89: 46071 | C89: P-9147.26 | D89: WEG | E89: FABRICANTE | F89: Ibaiti/PR | G89: Montagem Completa de 01 transformador de 230KV - COPEL | H89: COMERCIAL | I89: 46073 | J89: 46072 | K89: 18 | L89: 239900 | M89: 0.22 | N89: =IFERROR(Tabela225[[#This Row],[VALOR (R$)]]/Tabela225[[#This Row],[PRAZO EXECUÇÃO]],0) -> 13327.778 | O89: PERDIDA
A90: 80 | B90: 46072 | C90: P-9148.26 | D90: WEG | E90: FABRICANTE | F90: Maringa/PR | G90: Montagem Completa de 01 transformador de 230KV - COPEL | H90: COMERCIAL | I90: 46073 | J90: 46072 | K90: 18 | L90: 239900 | M90: 0.22 | N90: =IFERROR(Tabela225[[#This Row],[VALOR (R$)]]/Tabela225[[#This Row],[PRAZO EXECUÇÃO]],0) -> 13327.778 | O90: PERDIDA
A91: 81 | B91: 46072 | C91: P-9149.26 | D91: WEG | E91: FABRICANTE | F91: Confresa/MT | G91: Montagem completa de 01 transformador de 138kv - ENERGISA | H91: COMERCIAL | I91: 46076 | N91: =IFERROR(Tabela225[[#This Row],[VALOR (R$)]]/Tabela225[[#This Row],[PRAZO EXECUÇÃO]],0) -> 0 | O91: PERDIDA
A92: 82 | B92: 46072 | C92: P-9150.26 | D92: DATA | E92: FABRICANTE | F92: Franca/SP | G92: Montagem Completa de 01 transformador de 138KV - CPFL | H92: COMERCIAL | I92: 46083 | J92: 46072 | K92: 7 | L92: 75000 | M92: 0.2 | N92: =IFERROR(Tabela225[[#This Row],[VALOR (R$)]]/Tabela225[[#This Row],[PRAZO EXECUÇÃO]],0) -> 10714.286 | O92: APROVADA | P92: 46076 | Q92: 20123 | T92: RECEBIDO
A93: 83 | B93: 46072 | C93: P-9151.26 | D93: TBEA | E93: FABRICANTE | F93: Alegrete/RS | G93: Processo de vácuo e medição de URSI de um Transformador de 230KV | H93: COMERCIAL | N93: =IFERROR(Tabela225[[#This Row],[VALOR (R$)]]/Tabela225[[#This Row],[PRAZO EXECUÇÃO]],0) -> 0 | O93: PERDIDA
A94: 84 | B94: 46073 | C94: P-9166.26 | D94: WEG | E94: FABRICANTE | F94: Santos Dumont/MG | G94: Montagem Completa de 04 transformadores de 500kv - CYMI | H94: COMERCIAL | I94: 46078 | J94: 46076 | K94: =20*4 -> 80 | L94: 839800 | M94: 0.22 | N94: =IFERROR(Tabela225[[#This Row],[VALOR (R$)]]/Tabela225[[#This Row],[PRAZO EXECUÇÃO]],0) -> 10497.5 | O94: PERDIDA
A95: 2025 | B95: 46076 | C95: - | D95: WEG | E95: FABRICANTE | F95: Imperatriz/PI | G95: Aditivo - Estrutura adicional | H95: TÉCNICO | I95: 46076 | J95: 46076 | L95: 202370 | M95: 0.2 | N95: =IFERROR(Tabela225[[#This Row],[VALOR (R$)]]/Tabela225[[#This Row],[PRAZO EXECUÇÃO]],0) -> 0 | O95: APROVADA | P95: 46076 | S95: CONCLUÍDO | T95: RECEBIDO
A96: 2025 | B96: 46076 | C96: - | D96: WEG | E96: FABRICANTE | F96: Itapetininga/SP | G96: Aditivo - Diarias adicionais | H96: TÉCNICO | I96: 46076 | J96: 46076 | L96: 54500 | M96: 0.2 | N96: =IFERROR(Tabela225[[#This Row],[VALOR (R$)]]/Tabela225[[#This Row],[PRAZO EXECUÇÃO]],0) -> 0 | O96: APROVADA | P96: 46076 | S96: CONCLUÍDO | T96: RECEBIDO
A97: 85 | B97: 46076 | C97: P-9171.26 | D97: ENGIE | E97: CLIENTE FINAL | F97: Barueri/SP | G97: Reparo em Oficina de 01 Disjuntor de 36KV Schneider | H97: COMERCIAL | I97: 46076 | J97: 46076 | K97: 15 | L97: 21320 | M97: 0.2 | N97: =IFERROR(Tabela225[[#This Row],[VALOR (R$)]]/Tabela225[[#This Row],[PRAZO EXECUÇÃO]],0) -> 1421.3333 | O97: PERDIDA
A98: 86 | B98: 46076 | C98: P-9173.26 | D98: BR INFRA | E98: CLIENTE FINAL | F98: Fronteira/MG | G98: Desmontagem e rebaixamento de óleo de 04 transformadores de AT - USH DE MARIMBONDO | H98: COMERCIAL | I98: 46079 | J98: 46084 | K98: =5*4 -> 20 | L98: 249600 | M98: 0.3 | N98: =IFERROR(Tabela225[[#This Row],[VALOR (R$)]]/Tabela225[[#This Row],[PRAZO EXECUÇÃO]],0) -> 12480 | O98: NEGOCIAÇÃO
A99: 87 | B99: 46076 | C99: P-9174.26 | D99: WEG | E99: FABRICANTE | F99: Janaúba/MG | G99: Aditivo - Desmontagem de um transformador de 550kv - ELERA | H99: TÉCNICO | I99: 46078 | J99: 46079 | K99: 10 | L99: 123785 | M99: 0.29 | N99: =IFERROR(Tabela225[[#This Row],[VALOR (R$)]]/Tabela225[[#This Row],[PRAZO EXECUÇÃO]],0) -> 12378.5 | O99: APROVADA | P99: 46079 | Q99: 20040 | T99: RECEBIDO
A100: 88 | B100: 46076 | C100: P-9175.26 | D100: TSEA | E100: FABRICANTE | F100: Davinópolis/GO | G100: Manutenção Corretiva em 01 transformador de 138KV - USH Serra do Falcão | H100: COMERCIAL | I100: 46197 | J100: 46077 | K100: 6 | L100: =113500+76500 -> 190000 | M100: 0.27 | N100: =IFERROR(Tabela225[[#This Row],[VALOR (R$)]]/Tabela225[[#This Row],[PRAZO EXECUÇÃO]],0) -> 31666.667 | O100: PERDIDA
...

Sheet RESUMO ABERTAS_NEGOCIAÇÃO
A1: PROPOSTAS EM ABERTO E EM NEGOCIAÇÃO — 2026
A2: Base: aba CONTROLE DE PROPOSTAS_2026 (Tabela225). Tudo nesta aba é calculado por fórmula e atualiza sozinho.
J3: PARÂMETROS
A4: EM ANDAMENTO (TOTAL) | C4: EM ABERTO | E4: EM NEGOCIAÇÃO | G4: ="PARADAS HÁ +"&$K$6&" DIAS" -> PARADAS HÁ +60 DIAS | J4: Data de referência | K4: =TODAY() -> 46288
A5: =SUMIFS(Tabela225[VALOR (R$)],Tabela225[STATUS PROPOSTA],"EM ABERTO")+SUMIFS(Tabela225[VALOR (R$)],Tabela225[STATUS PROPOSTA],"NEGOCIAÇÃO") -> 68457618 | C5: =SUMIFS(Tabela225[VALOR (R$)],Tabela225[STATUS PROPOSTA],"EM ABERTO") -> 65051761 | E5: =SUMIFS(Tabela225[VALOR (R$)],Tabela225[STATUS PROPOSTA],"NEGOCIAÇÃO") -> 3405857 | G5: {=_xlfn.LET(_xlpm.st,Tabela225[STATUS PROPOSTA],_xlpm.dt,Tabela225[DT. ABERTURA],_xlpm.vl,Tabela225[VALOR (R$)],_xlpm.d,IF(ISNUMBER(_xlpm.dt),$K$4-_xlpm.dt,-1),_xlpm.f,((_xlpm.st="EM ABERTO")+(_xlpm.st="NEGOCIAÇÃO"))*(_xlpm.d>=$K$6),SUM(_xlpm.f*IF(ISNUMBER(_xlpm.vl),_xlpm.vl,0)))} -> 41544668 | J5: Régua de tempo (dias em aberto)
J6: 🔴 Crítico — a partir de | K6: 60
A7: =_xlfn.LET(_xlpm.q,COUNTIFS(Tabela225[STATUS PROPOSTA],"EM ABERTO")+COUNTIFS(Tabela225[STATUS PROPOSTA],"NEGOCIAÇÃO"),_xlpm.q&" propostas • ticket médio "&TEXT(IFERROR($A$5/_xlpm.q,0),"R$ #.##0")) -> 121 propostas • ticket médio R$ 565.765 | C7: =_xlfn.LET(_xlpm.q,COUNTIFS(Tabela225[STATUS PROPOSTA],"EM ABERTO"),_xlpm.q&" propostas • "&TEXT(IFERROR($C$5/$A$5,0),"0,0%")&" do valor") -> 109 propostas • 95,0% do valor | E7: =_xlfn.LET(_xlpm.q,COUNTIFS(Tabela225[STATUS PROPOSTA],"NEGOCIAÇÃO"),_xlpm.q&" propostas • "&TEXT(IFERROR($E$5/$A$5,0),"0,0%")&" do valor") -> 12 propostas • 5,0% do valor | G7: {=_xlfn.LET(_xlpm.st,Tabela225[STATUS PROPOSTA],_xlpm.dt,Tabela225[DT. ABERTURA],_xlpm.d,IF(ISNUMBER(_xlpm.dt),$K$4-_xlpm.dt,-1),_xlpm.q,SUM(((_xlpm.st="EM ABERTO")+(_xlpm.st="NEGOCIAÇÃO"))*(_xlpm.d>=$K$6)),_xlpm.q&" propostas • "&TEXT(IFERROR($G$5/$A$5,0),"0,0%")&" do valor")} -> 57 propostas • 60,7% do valor | J7: 🟠 Atenção — a partir de | K7: 30
J8: 🟡 Morno — a partir de | K8: 15
A9: HÁ QUANTO TEMPO A PROPOSTA ESTÁ PARADA (contado da data de abertura) | J9: 🟢 Recente — abaixo de 15 dias
A10: FAIXA | B10: DE (dias) | C10: ATÉ (dias) | D10: QTD | E10: VALOR (R$) | F10: % DO VALOR
A11: 🔴 Crítico | B11: =$K$6 -> 60 | C11: 99999 | D11: {=_xlfn.LET(_xlpm.st,Tabela225[STATUS PROPOSTA],_xlpm.dt,Tabela225[DT. ABERTURA],_xlpm.d,IF(ISNUMBER(_xlpm.dt),$K$4-_xlpm.dt,-1),SUM(((_xlpm.st="EM ABERTO")+(_xlpm.st="NEGOCIAÇÃO"))*(_xlpm.d>=$B11)*(_xlpm.d<=$C11)))} -> 57 | E11: {=_xlfn.LET(_xlpm.st,Tabela225[STATUS PROPOSTA],_xlpm.dt,Tabela225[DT. ABERTURA],_xlpm.vl,Tabela225[VALOR (R$)],_xlpm.d,IF(ISNUMBER(_xlpm.dt),$K$4-_xlpm.dt,-1),SUM(((_xlpm.st="EM ABERTO")+(_xlpm.st="NEGOCIAÇÃO"))*(_xlpm.d>=$B11)*(_xlpm.d<=$C11)*IF(ISNUMBER(_xlpm.vl),_xlpm.vl,0)))} -> 41544668 | F11: =IFERROR(E11/$E$16,0) -> 0.60686697
A12: 🟠 Atenção | B12: =$K$7 -> 30 | C12: =$K$6-1 -> 59 | D12: {=_xlfn.LET(_xlpm.st,Tabela225[STATUS PROPOSTA],_xlpm.dt,Tabela225[DT. ABERTURA],_xlpm.d,IF(ISNUMBER(_xlpm.dt),$K$4-_xlpm.dt,-1),SUM(((_xlpm.st="EM ABERTO")+(_xlpm.st="NEGOCIAÇÃO"))*(_xlpm.d>=$B12)*(_xlpm.d<=$C12)))} -> 37 | E12: {=_xlfn.LET(_xlpm.st,Tabela225[STATUS PROPOSTA],_xlpm.dt,Tabela225[DT. ABERTURA],_xlpm.vl,Tabela225[VALOR (R$)],_xlpm.d,IF(ISNUMBER(_xlpm.dt),$K$4-_xlpm.dt,-1),SUM(((_xlpm.st="EM ABERTO")+(_xlpm.st="NEGOCIAÇÃO"))*(_xlpm.d>=$B12)*(_xlpm.d<=$C12)*IF(ISNUMBER(_xlpm.vl),_xlpm.vl,0)))} -> 14902642 | F12: =IFERROR(E12/$E$16,0) -> 0.21769151
A13: 🟡 Morno | B13: =$K$8 -> 15 | C13: =$K$7-1 -> 29 | D13: {=_xlfn.LET(_xlpm.st,Tabela225[STATUS PROPOSTA],_xlpm.dt,Tabela225[DT. ABERTURA],_xlpm.d,IF(ISNUMBER(_xlpm.dt),$K$4-_xlpm.dt,-1),SUM(((_xlpm.st="EM ABERTO")+(_xlpm.st="NEGOCIAÇÃO"))*(_xlpm.d>=$B13)*(_xlpm.d<=$C13)))} -> 13 | E13: {=_xlfn.LET(_xlpm.st,Tabela225[STATUS PROPOSTA],_xlpm.dt,Tabela225[DT. ABERTURA],_xlpm.vl,Tabela225[VALOR (R$)],_xlpm.d,IF(ISNUMBER(_xlpm.dt),$K$4-_xlpm.dt,-1),SUM(((_xlpm.st="EM ABERTO")+(_xlpm.st="NEGOCIAÇÃO"))*(_xlpm.d>=$B13)*(_xlpm.d<=$C13)*IF(ISNUMBER(_xlpm.vl),_xlpm.vl,0)))} -> 9673267 | F13: =IFERROR(E13/$E$16,0) -> 0.141303
A14: 🟢 Recente | B14: 0 | C14: =$K$8-1 -> 14 | D14: {=_xlfn.LET(_xlpm.st,Tabela225[STATUS PROPOSTA],_xlpm.dt,Tabela225[DT. ABERTURA],_xlpm.d,IF(ISNUMBER(_xlpm.dt),$K$4-_xlpm.dt,-1),SUM(((_xlpm.st="EM ABERTO")+(_xlpm.st="NEGOCIAÇÃO"))*(_xlpm.d>=$B14)*(_xlpm.d<=$C14)))} -> 14 | E14: {=_xlfn.LET(_xlpm.st,Tabela225[STATUS PROPOSTA],_xlpm.dt,Tabela225[DT. ABERTURA],_xlpm.vl,Tabela225[VALOR (R$)],_xlpm.d,IF(ISNUMBER(_xlpm.dt),$K$4-_xlpm.dt,-1),SUM(((_xlpm.st="EM ABERTO")+(_xlpm.st="NEGOCIAÇÃO"))*(_xlpm.d>=$B14)*(_xlpm.d<=$C14)*IF(ISNUMBER(_xlpm.vl),_xlpm.vl,0)))} -> 2337041 | F14: =IFERROR(E14/$E$16,0) -> 0.034138509
A15: ⚠ Data de abertura inválida/futura na base | D15: {=_xlfn.LET(_xlpm.st,Tabela225[STATUS PROPOSTA],_xlpm.dt,Tabela225[DT. ABERTURA],_xlpm.d,IF(ISNUMBER(_xlpm.dt),$K$4-_xlpm.dt,-1),SUM(((_xlpm.st="EM ABERTO")+(_xlpm.st="NEGOCIAÇÃO"))*(_xlpm.d<0)))} -> 0 | E15: {=_xlfn.LET(_xlpm.st,Tabela225[STATUS PROPOSTA],_xlpm.dt,Tabela225[DT. ABERTURA],_xlpm.vl,Tabela225[VALOR (R$)],_xlpm.d,IF(ISNUMBER(_xlpm.dt),$K$4-_xlpm.dt,-1),SUM(((_xlpm.st="EM ABERTO")+(_xlpm.st="NEGOCIAÇÃO"))*(_xlpm.d<0)*IF(ISNUMBER(_xlpm.vl),_xlpm.vl,0)))} -> 0 | F15: =IFERROR(E15/$E$16,0) -> 0
A16: TOTAL | D16: =SUM(D11:D15) -> 121 | E16: =SUM(E11:E15) -> 68457618 | F16: =IFERROR(E16/$E$16,0) -> 1
A17: =IF(D15=0,"","⚠ "&D15&" proposta(s) com DT. ABERTURA incorreta na aba CONTROLE DE PROPOSTAS_2026 — corrigir para entrarem na régua de tempo.")
A18: DETALHAMENTO — PROPOSTAS EM ABERTO E EM NEGOCIAÇÃO (das mais paradas para as mais recentes)
A19: DT. ABERTURA | B19: DIAS PARADO | C19: SITUAÇÃO | D19: Nº PROPOSTA | E19: CLIENTE | F19: STATUS | G19: VALOR (R$) | H19: MARGEM | I19: TÉCNICO | J19: LOCAL EXECUÇÃO | K19: DESCRIÇÃO DOS SERVIÇOS
A20: {=_xlfn.LET(_xlpm.st,Tabela225[STATUS PROPOSTA],_xlpm.dt,Tabela225[DT. ABERTURA],_xlpm.vl,Tabela225[VALOR (R$)],_xlpm.d,IF(ISNUMBER(_xlpm.dt),$K$4-_xlpm.dt,-1),_xlpm.cls,IF(_xlpm.d<0,"⚠ Data inválida",IF(_xlpm.d>=$K$6,"🔴 Crítico",IF(_xlpm.d>=$K$7,"🟠 Atenção",IF(_xlpm.d>=$K$8,"🟡 Morno","🟢 Recente")))),_xlpm.base,_xlfn.HSTACK(IF(ISNUMBER(_xlpm.dt),_xlpm.dt,""),_xlpm.d,_xlpm.cls,Tabela225[Nº PROPOSTA],Tabela225[CLIENTE],_xlpm.st,IF(ISNUMBER(_xlpm.vl),_xlpm.vl,0),Tabela225[MARGEM],Tabela225[TÉCNICO],Tabela225[LOCAL EXECUÇÃO],Tabela225[DESCRIÇÃO DOS SERVIÇOS]),_xlfn._xlws.SORT(_xlfn._xlws.FILTER(_xlpm.base,(_xlpm.st="EM ABERTO")+(_xlpm.st="NEGOCIAÇÃO")),2,-1))} -> 46027 | B20: 261 | C20: 🔴 Crítico | D20: P-3668 | E20: Suzano Papel e Celulose | F20: NEGOCIAÇÃO | G20: 300000 | H20: 0.2 | I20: COMERCIAL | J20: Três Lagoas/MS | K20: Manutenção Preventiva e Corretiva em Transformadores
A21: 46037 | B21: 251 | C21: 🔴 Crítico | D21: P-8912.26 | E21: ALUPAR | F21: EM ABERTO | G21: 319960.1 | H21: 0.22 | I21: COMERCIAL | J21: Varzea Grande/MT | K21: Manutenção corretiva em 01 transformador de 230KV - TRANSMISSÃO DE VARZEA
A22: 46052 | B22: 236 | C22: 🔴 Crítico | D22: P-9020.26 | E22: CHINT | F22: EM ABERTO | G22: 406162 | H22: 0.23 | I22: COMERCIAL | J22: Ferreiras Gomes/AP | K22: Montagem Completa de 01 transformador de 230KV - ELETROBRAS
A23: 46057 | B23: 231 | C23: 🔴 Crítico | D23: P-9046.26 | E23: CELEO | F23: EM ABERTO | G23: 449900 | H23: 0.26 | I23: COMERCIAL | J23: Nova Ponte/MG | K23: Manutenção Corretiva de 03 reatores de 500KV - CELEO
A24: 46076 | B24: 212 | C24: 🔴 Crítico | D24: P-9173.26 | E24: BR INFRA | F24: NEGOCIAÇÃO | G24: 249600 | H24: 0.3 | I24: COMERCIAL | J24: Fronteira/MG | K24: Desmontagem e rebaixamento de óleo de 04 transformadores de AT - USH DE MARIMBONDO
A25: 46084 | B25: 204 | C25: 🔴 Crítico | D25: P-9245.26 | E25: BR INFRA | F25: NEGOCIAÇÃO | G25: 98000 | H25: 0.2 | I25: COMERCIAL | J25: Rio Verde/GO | K25: Desmontagem e Drenagem de 04 autotransformadores de 230KV
A26: 46084 | B26: 204 | C26: 🔴 Crítico | D26: P-9247.26 | E26: BR INFRA | F26: NEGOCIAÇÃO | G26: 79150 | H26: 0.2 | I26: COMERCIAL | J26: Barro Alto/GO | K26: Desmontagem e Drenagem de 03 autotransformadores de 230KV
A27: 46086 | B27: 202 | C27: 🔴 Crítico | D27: P-9266.26 | E27: CHINT | F27: EM ABERTO | G27: 5420996 | H27: 0.26 | I27: COMERCIAL | J27: Nordestes/ CE e RN | K27: Montagem Completa de Transformadores de AT - CHINT
A28: 46097 | B28: 191 | C28: 🔴 Crítico | D28: P-9340.26 | E28: CARGILL | F28: EM ABERTO | G28: 95460 | H28: 0.25 | I28: COMERCIAL | J28: Uberlandia/MG | K28: Manutenção Corretiva em Transformadores de BT - CARGIL
A29: 46099 | B29: 189 | C29: 🔴 Crítico | D29: P-9365.26 | E29: Naturgy | F29: EM ABERTO | G29: 334900 | H29: 0.21 | I29: COMERCIAL | J29: Piauí/PI | K29: Manutenção Corretiva em transformadores de 0,69/34,5 KV - NATURGY
A30: 46120 | B30: 168 | C30: 🔴 Crítico | D30: P-9496.26 | E30: WEG | F30: NEGOCIAÇÃO | G30: 49900 | H30: 0.19 | I30: TÉCNICO | J30: Luziania/GO | K30: ADITIVO - Mobilização e Desmobilização adicional da equipe/equipamentos e tanque auxiliar - EQUATORIAL
A31: 46126 | B31: 162 | C31: 🔴 Crítico | D31: P-9544.26 | E31: Hitachi | F31: EM ABERTO | G31: 298604 | H31: 0.22 | I31: COMERCIAL | J31: Pindamonhangaba/SP | K31: Montagem Completa de 02 transformadores de 138kv - Hitachi
A32: 46132 | B32: 156 | C32: 🔴 Crítico | D32: P-9583.26 | E32: WEG | F32: NEGOCIAÇÃO | G32: 30790 | H32: 0.25 | I32: TÉCNICO | J32: Pirajuba/MG | K32: ADITIVO - Mobilização e Desmobilização da Equipe e equipamento - USINA SANTO ANGELO
... A108: 46258 | B108: 30 | C108: 🟠 Atenção | D108: P-10384.26 | E108: WEG | F108: EM ABERTO | G108: 269700 | H108: 0.27 | I108: COMERCIAL | J108: Ribeirão Preto/SP | K108: Tratamento, Enchimento e comissionamento de 03 reatores de 500KV - STATE GRID
A109: 46258 | B109: 30 | C109: 🟠 Atenção | D109: P-10385.26 | E109: Volkswagen | F109: EM ABERTO | G109: 4785000 | H109: % | I109: COMERCIAL | J109: São Bernardo do Campo/SP | K109: Fornecimento de Novo Transformador - VOLKSWAGEN
A110: 46258 | B110: 30 | C110: 🟠 Atenção | D110: P-10386.26 | E110: Volkswagen | F110: EM ABERTO | G110: 100000 | H110: % | I110: COMERCIAL | J110: São Bernardo do Campo/SP | K110: Compra de Transformadores para Descarte - VOLKSWAGEN
A111: 46258 | B111: 30 | C111: 🟠 Atenção | D111: P-10387.26 | E111: Volkswagen | F111: EM ABERTO | G111: 677010 | H111: 0.25 | I111: COMERCIAL | J111: São Bernardo do Campo/SP | K111: Manutenção Corretiva de Transformadores - VOLKSWAGEN
A112: 46258 | B112: 30 | C112: 🟠 Atenção | D112: P-10390.26 | E112: PETROBRAS | F112: EM ABERTO | G112: 466240 | H112: 0.26 | I112: COMERCIAL | J112: Cubatão/SP | K112: Manutenção Corretiva em Transformadores de AT - PETROBRAS
A113: 46258 | B113: 30 | C113: 🟠 Atenção | D113: P-10399.26 | E113: PROMON ENGENHARIA | F113: EM ABERTO | G113: 189514 | H113: 0.3 | I113: COMERCIAL | J113: Camaçari/BA | K113: Inspeção e Ensaios Elétricos em transformadores de AT
A114: 46259 | B114: 29 | C114: 🟡 Morno | D114: P-10403.26 | E114: WEG | F114: EM ABERTO | G114: 278900 | H114: 0.25 | I114: COMERCIAL | J114: Santa Rosa/RS | K114: Montagem Completa de 01 transformador trifásico de 230KV - CPFL
A115: 46260 | B115: 28 | C115: 🟡 Morno | D115: P-10405.26 | E115: PROMON ENGENHARIA | F115: EM ABERTO | G115: 319280 | H115: 0.3 | I115: COMERCIAL | J115: Camaçari/BA | K115: Inspeção e Ensaios Elétricos em transformadores de AT
A116: 46262 | B116: 26 | C116: 🟡 Morno | D116: P-10423.26 | E116: WEG | F116: EM ABERTO | G116: 173415 | H116: 0.25 | I116: COMERCIAL | J116: Uberlandia/MG | K116: Montagem Completa em 01 transformador de 138KV - CEMIG
A117: 46265 | B117: 23 | C117: 🟡 Morno | D117: P-10443.26 | E117: CPFL Transmissões | F117: EM ABERTO | G117: 0 | H117: 0 | I117: COMERCIAL | J117: Mogi das Cruzes/SP | K117: Recebimento, Transposte, Montagem e comissionamento de 10 transformadores - CPFL
A118: 46265 | B118: 23 | C118: 🟡 Morno | D118: P-10445.26 | E118: CPFL Transmissões | F118: EM ABERTO | G118: 0 | H118: 0 | I118: COMERCIAL | J118: Santa Terezinha de Itapu/PR | K118: Recebimento, Transposte, Montagem e comissionamento de 10 transformadores - CPFL
A119: 46267 | B119: 21 | C119: 🟡 Morno | D119: P-10450.26 | E119: Chint | F119: EM ABERTO | G119: 2646344 | H119: 0.25 | I119: COMERCIAL | J119: Mogi das Cruzes/SP | K119: Montagem Completa de 10 transformadores monofásico de 500KV - CPFL
A120: 46267 | B120: 21 | C120: 🟡 Morno | D120: P-10451.26 | E120: Chint | F120: EM ABERTO | G120: 551278 | H120: 0.25 | I120: COMERCIAL | J120: Pirapora/MG | K120: Montagem Completa de 02 transformadores Trifásco de 138KV - EDP
A121: 46267 | B121: 21 | C121: 🟡 Morno | D121: P-10452.26 | E121: Chint | F121: EM ABERTO | G121: 1196990 | H121: 0.25 | I121: COMERCIAL | J121: Cassilandia/MS | K121: Montagem Completa de 04 Autotransformadores Mnofásico 500KV - ANEEL
A122: 46267 | B122: 21 | C122: 🟡 Morno | D122: P-10453.26 | E122: WEG | F122: EM ABERTO | G122: 194245 | H122: 0.26 | I122: COMERCIAL | J122: Vila Velha/ES | K122: Montagem Completa de 01 transformadores Mnofásico 138KV - EDP
... A124: 46267 | B124: 21 | C124: 🟡 Morno | D124: P-10455.26 | E124: Lerose | F124: EM ABERTO | G124: 0 | H124: 0 | I124: COMERCIAL | J124: Suzano/SP | K124: Manutenção Corretiva em Transformadores de 88KV - KOMATSU
A125: 46267 | B125: 21 | C125: 🟡 Morno | D125: P-10460.26 | E125: Volkswagen | F125: EM ABERTO | G125: 3800000 | H125: % | I125: COMERCIAL | J125: São Bernardo do Campo/SP | K125: Reparo em transformadores de Fabrica - Volkswagem
A126: 46273 | B126: 15 | C126: 🟡 Morno | D126: P-10478.26 | E126: WEG | F126: EM ABERTO | G126: 323875 | H126: 0.25 | I126: COMERCIAL | J126: Canoas/RS | K126: Montagem Completa de 01 transformador de 230KV - CPFL
A127: 46274 | B127: 14 | C127: 🟢 Recente | D127: P-10486.26 | E127: Estel | F127: EM ABERTO | G127: 691130 | H127: 0.25 | I127: COMERCIAL | J127: Vitoria/ES | K127: Remoção de Gás e tratamento de óleo em transformadores de AT - VALE
A128: 46275 | B128: 13 | C128: 🟢 Recente | D128: P-10500.26 | E128: WEG | F128: EM ABERTO | G128: 84695 | H128: 0.25 | I128: COMERCIAL | J128: Brasilia/DF | K128: Manutenção Corretiva em 01 transformador de 138KV - NEOENERGIA
A129: 46275 | B129: 13 | C129: 🟢 Recente | D129: P-10502.26 | E129: WEG | F129: EM ABERTO | G129: 111720 | H129: 0.25 | I129: COMERCIAL | J129: Sento da Sé/BA | K129: Comissionamento em Campo de 04 transformadores - BRENNAND
A130: 46276 | B130: 12 | C130: 🟢 Recente | D130: P-10508.26 | E130: Comerc Energia | F130: EM ABERTO | G130: 0 | H130: 0 | I130: COMERCIAL | J130: Fazenda Nova/PE | K130: Tratamento de óleo isolante em transformadores - BRIGIDA SOLAR
A131: 46276 | B131: 12 | C131: 🟢 Recente | D131: P-10509.26 | E131: WEG | F131: EM ABERTO | G131: 719600 | H131: 0.25 | I131: COMERCIAL | J131: Campinas/SP | K131: Montagem Completa de 04 transformadores de 330KV - AXIA
A132: 46276 | B132: 12 | C132: 🟢 Recente | D132: P-10511.26 | E132: WEG | F132: EM ABERTO | G132: 169200 | H132: 0.25 | I132: COMERCIAL | J132: Imbituba/SC | K132: Montagem Completa de 01 transformador de 138KV - CELESC
A133: 46276 | B133: 12 | C133: 🟢 Recente | D133: P-10513.26 | E133: WEG | F133: EM ABERTO | G133: 196890 | H133: 0.25 | I133: COMERCIAL | J133: São João do Piaui-PI | K133: Montagem Completa de 01 transformador de 230kv - CNS/AXIA
A134: 46276 | B134: 12 | C134: 🟢 Recente | D134: P-10519.26 | E134: WEG | F134: EM ABERTO | G134: 20985 | H134: 0.23 | I134: COMERCIAL | J134: Serra/ES | K134: Correção de pendencias em um transformador - ARCELORMITTAL
A135: 46280 | B135: 8 | C135: 🟢 Recente | D135: P-10527.26 | E135: WEG | F135: EM ABERTO | G135: 22997 | H135: 0.23 | I135: COMERCIAL | J135: Barueri/SP | K135: Manutenção Corretiva em 01 transformador de 34,5KV - ENGEMON
A136: 46280 | B136: 8 | C136: 🟢 Recente | D136: P-10530.26 | E136: Ferrari Agroindustria | F136: EM ABERTO | G136: 10049 | H136: 0.23 | I136: COMERCIAL | J136: Leme/SP | K136: Coleta de Amostra de óleo para analise em 13 transformaodores - CRESCIUMAL BIOENERGIA
A137: 46280 | B137: 8 | C137: 🟢 Recente | D137: P-10532.26 | E137: Biancogres | F137: EM ABERTO | G137: 107765 | H137: 0.23 | I137: COMERCIAL | J137: Serra/ES | K137: Manutenção Corretiva em 02 transformadores de AT - BIANCOGRES
... A140: 46283 | B140: 5 | C140: 🟢 Recente | D140: P-10559.26 | E140: BLUTRAFOS | F140: EM ABERTO | G140: 108650 | H140: 0.25 | I140: COMERCIAL | J140: Telêmaco Borba/PR | K140: Desmontagem Completa de 01 transformador de 69KV - BLUTRAFOS

Sheet ESCOPO PROPOSTAS 
D1: PROPOSTA-SRV.04158.22 | I1: PROPOSTA-SRV.04154.22 | N1: PROPOSTA-SRV.04151.22 | S1: PROPOSTA-SRV.04147.22 | X1: PROPOSTA-SRV.04145.22 | AC1: PROPOSTA-SRV.04141.22 | AH1: PROPOSTA-SRV.04140.22 | AM1: PROPOSTA-SRV.04136.22 | AR1: PROPOSTA-SRV.04127.22 | AW1: PROPOSTA-SRV.04120.22.A | BB1: PROPOSTA-SRV.04114.22 | BG1: PROPOSTA-SRV.04109.22 | BL1: PROPOSTA-SRV.04106.22 | BQ1: PROPOSTA-SRV.04105.22 | BV1: PROPOSTA-SRV.04102.22 | CA1: PROPOSTA-SRV.04100.22 | CF1: PROPOSTA-SRV.04098.22 | CK1: PROPOSTA-SRV.04094.22 | CP1: PROPOSTA-SRV.04080.22 | CU1: PROPOSTA-SRV.04078.22 | CZ1: PROPOSTA-SRV.04072.22 | DE1: PROPOSTA-SRV.04056.22 | DJ1: PROPOSTA-SRV.04032.22 | DO1: PROPOSTA-SRV.04019.22 | DT1: PROPOSTA-SRV.04010.22 | DZ1: PROPOSTA-SRV.04003.22 | EE1: PROPOSTA-SRV.04002.22 | EJ1: PROPOSTA-SRV.03998.22 | EO1: PROPOSTA-SRV.03979.22 | EW1: PROPOSTA-SRV.03974.22 | FB1: PROPOSTA-SRV.03969.22 | FG1: PROPOSTA-SRV.03960.22 | FL1: PROPOSTA-SRV.03956.22 | FQ1: PROPOSTA-SRV.03954.22 | FV1: PROPOSTA-SRV.03953.22 | GA1: PROPOSTA-SRV.03947.22 | GI1: PROPOSTA-SRV.03943.22 | GN1: PROPOSTA-SRV.03940.22 | GS1: PROPOSTA-SRV.03933.22 | GY1: PROPOSTA-SRV.03926.22 | HD1: PROPOSTA-SRV.03920.22 | HI1: PROPOSTA-SRV.03922.22
D3: Cliente: WEG - CPFL | I3: Cliente: TSEA - ARCELORMITTAL | N3: Cliente: COMTRAFO | S3: Cliente: ENGELMIG | X3: Cliente: WEG - CEMIG | AC3: Cliente: TSEA | AH3: Cliente: ENERWATT- WEG - | AM3: Cliente: WEG - EDP | AR3: Cliente: WEG - CGT ELETROSUL | AW3: Cliente: CPFL TRANSMISSÃO | BC3: Cliente: WEG - SIMM | BH3: Cliente: NARI | BM3: Cliente: WEG - MEZ ENERGIA | BQ3: Cliente: WEG - OMEGA DESENV. DE ENERGIA 3 | BW3: Cliente: TSEA - RGE SUL - CPFL | CB3: Cliente: TSEA - UHE SALTO PILÃO | CG3: Cliente: WEG - CHESF | CL3: Cliente: WEG - CELG | CQ3: Cliente: WEG - ABB - ANEMUS WIND | CV3: Cliente: TSEA - CYMIMASA | DA3: Cliente: EVOLTZ | DF3: Cliente: TSEA - COPEL | DK3: Cliente: SENDI | DP3: CLIENTE: WEG - FURNAS CENTRAIS ELETRICAS | DU3: Cliente: CELSE | EA3: Cliente: TSEA | EF3: Cliente: TSEA | EK3: CLIENTE: WEG - CNS | EP3: CLIENTE: ENERGISA | EX3: CLIENTE: COOP RUBI | FC3: CLIENTE: COPEL | FH3: Cliente: SNEF-ENERG POWER | FM3: Cliente: ENERGISA | FR3: Cliente: ABB | FW3: Cliente: BEM BRASIL | GA3: Cliente: WEG - ENERGISA | GJ3: Cliente: ENERGISA | GO3: Cliente: ENERGISA | GT3: Cliente: NEOENERGIA | GW3: SERVIÇOS: | GZ3: Cliente: CARAMURU | HE3: Cliente: PARQUE EÓLICO SERRA DO SERIDÓ VI | HJ3: Cliente: TECNOVA
GW4: Substituição da Válvula Borboleta
E5: Escopo: | J5: Escopo: | O5: Escopo: | T5: Escopo: | Y5: Escopo: | AD5: Escopo: | AI5: Escopo: | AN5: Escopo: | AS5: Escopo: | AX5: Escopo: | BC5: Escopo: | BH5: Escopo: | BM5: Escopo: | BR5: Escopo: | BW5: Escopo: | CB5: Escopo: | CG5: Escopo: | CL5: Escopo: | CQ5: Escopo: | CV5: Escopo: | DA5: Escopo: | DF5: Escopo: | DK5: Escopo: | DP5: Escopo : | DU5: Escopo: | EA5: Escopo: | EF5: Escopo: | EK5: Escopo : | EP5: Escopo : | ES5: Escopo : | EX5: Escopo : | FC5: Escopo : | FH5: Escopo 1 | FM5: Escopo 1 | FR5: Escopo 1 | FW5: Escopo 1 | GB5: CP: 16102924 | GJ5: Escopo 1 | GO5: Escopo 1 | GT5: Escopo 1 | GZ5: Escopo: | HE5: Escopo: | HJ5: Escopo:
E6: Equipamento: | F6: Autotransformador | J6: Equipamento: | K6: Transformador | O6: Equipamento: | P6: Transformador | T6: Equipamento: | U6: Transformador | Y6: Equipamento: | Z6: AutoTransformador | AD6: Equipamento: | AE6: Transformador | AI6: Equipamento: | AJ6: Transformador | AN6: Equipamento: | AO6: Transformador | AS6: Equipamento: | AT6: Transformador | AX6: Equipamento: | AY6: Transformador | BC6: Equipamento: | BD6: Transformador Regulador | BH6: Equipamento: | BI6: Transformador | BM6: Equipamento: | BN6: Transformador | BR6: Equipamento: | BS6: Transformador | BW6: Equipamento: | BX6: Transformador | CB6: Equipamento: | CC6: Transformador Elevador | CG6: Equipamento: | CH6: Transformador Elevador | CL6: Equipamento: | CM6: Autotransformador Regulador | CQ6: Equipamento: | CR6: Transformador | CV6: Equipamento: | CW6: REATOR | DA6: Equipamento: | DB6: Autotransformadores | DF6: Equipamento: | DG6: Transformador | DK6: Equipamento: | DL6: Transformador | DP6: Equipamento: | DQ6: Autotransformador | DU6: Equipamento: | DV6: Transformador | EA6: Equipamento: | EB6: Transformador | EF6: Equipamento: | EG6: Transformador | EK6: Equipamento: | EL6: Transformador | EP6: Equipamento: | EQ6: Autotransformador | ES6: Equipamento: | ET6: Reator | EX6: Equipamento: | EY6: Transformador | FC6: Equipamento: | FD6: Autotransformador | FH6: Equipamento: | FI6: Transformador | FM6: Equipamento: | FN6: Reator | FR6: Equipamento: | FS6: Transformador | FW6: Equipamento: | FX6: Transformador | GB6: Equipamento: | GC6: Transformador | GE6: Serviço: Inspeção Recebimento, Montagem, Tratamento da Parte Ativa, Tratamento de Óleo, Comissionamento e Start-Up. --------------------------------------------------------- CP:16102924 Cliente: ENERGISA - 01 (um) Transformador de Potência Trifásico 15MVAr -138kV - 17.063 Litros de óleo (Equip. transp. com óleo) Local : Chapada dos Guimarães / MT --------------------------------------------------------- CP:16103020 Cliente: ENERGISA - 01 (um) Transformador de Potência Trifásico 15MVAr -138kV - 13.660 Litros de óleo (Equip. transp. com óleo) Local : Diamantina / MT --------------------------------------------------------- CP:16127767 (2x) Cliente: ENERGISA - 01 (um) Transformador de Potência Trifásico 15MVAr -138kV - 18.050 Litros de óleo (Equip. transp. com óleo) Local : Nova Mutum / MT + Lucas do Rio Verde / MT | GJ6: Equipamento: | GK6: Reator | GO6: Equipamento: | GP6: Transformador | GT6: Equipamento: | GU6: Reator | GW6: CP: 180279109 Cliente: NEOENERGIA Substituição de Válvula Borboleta 01 (um) Reator Monofásico 66,7MVA -500kV - Gilbués / PI | GZ6: Equipamento: | HA6: Transformador | HE6: Equipamento: | HF6: Transformador | HJ6: Equipamento: | HK6: Transformador
E7: Quantidade: | F7: 7 | J7: Quantidade: | K7: 1 | O7: Quantidade: | P7: 1 | T7: Quantidade: | U7: 1 | Y7: Quantidade: | Z7: 1 | AD7: Quantidade: | AE7: 1 | AI7: Quantidade: | AJ7: 1 | AN7: Quantidade: | AO7: 3 | AS7: Quantidade: | AT7: 2 | AX7: Quantidade: | AY7: 1 | BC7: Quantidade: | BD7: 2 | BH7: Quantidade: | BI7: 1 | BM7: Quantidade: | BN7: 2 | BR7: Quantidade: | BS7: 2 | BW7: Quantidade: | BX7: 1 | CB7: Quantidade: | CC7: 2 | CG7: Quantidade: | CH7: 20 | CL7: Quantidade: | CM7: 1 | CQ7: Quantidade: | CR7: 1 | CV7: Quantidade: | CW7: 1 | DA7: Quantidade: | DB7: BANCO/DOIS | DF7: Quantidade: | DG7: 2 | DK7: Quantidade: | DL7: 1 | DP7: Quantidade: | DQ7: 4 | DU7: Quantidade: | DV7: 1 | EA7: Quantidade: | EB7: 1 | EF7: Quantidade: | EG7: 4 | EK7: Quantidade: | EL7: 1 | EP7: Quantidade: | EQ7: 4 | ES7: Quantidade: | ET7: 4 | EX7: Quantidade: | EY7: 1 | FC7: Quantidade: | FD7: 1 | FH7: Quantidade: | FI7: 2 | FM7: Quantidade: | FN7: 1 | FR7: Quantidade: | FS7: 1 | FW7: Quantidade: | FX7: 1 | GB7: Quantidade: | GC7: 1 | GJ7: Quantidade: | GK7: 1 | GO7: Quantidade: | GP7: 1 | GT7: Quantidade: | GU7: 1 | GZ7: Quantidade: | HA7: 11 | HE7: Quantidade: | HF7: 1 | HJ7: Quantidade: | HK7: 2
E8: Fases: | F8: Monofásico | J8: Fases: | K8: Trifásico | O8: Fases: | P8: Trifásico | T8: Fases: | U8: Trifásico | Y8: Fases: | Z8: Monofásico | AD8: Fases: | AE8: Monofásico | AI8: Fases: | AJ8: Trifásico | AN8: Fases: | AO8: - | AS8: Fases: | AT8: Trifásico | AX8: Fases: | AY8: Monofásico | BC8: Fases: | BD8: Trifásico | BH8: Fases: | BI8: Trifásico | BM8: Fases: | BN8: Trifásico | BR8: Fases: | BS8: Trifásico | BW8: Fases: | BX8: Trifásico | CB8: Fases: | CC8: Monofásico | CG8: Fases: | CH8: Monofásico | CL8: Fases: | CM8: Monofásico | CQ8: Fases: | CR8: Trifásico | CV8: Fases: | CW8: Monofásico | DA8: Fases: | DB8: Monofásico/Trifásicos | DF8: Fases: | DG8: Trifásico | DK8: Fases: | DL8: Trifásico | DP8: Fases: | DQ8: Monofásico | DU8: Fases: | DV8: Trifásico | EA8: Fases: | EB8: Trifásico | EF8: Fases: | EG8: Monofásico | EK8: Fases: | EL8: Trifásico | EP8: Fases: | EQ8: Monofásico | ES8: Fases: | ET8: Monofásico | EX8: Fases: | EY8: Trifásico | FC8: Fases: | FD8: Trifásico | FH8: Fases: | FI8: Trifásico | FM8: Fases: | FN8: Trifásico | FR8: Fases: | FS8: Trifásico | FW8: Fases: | FX8: Trifásico | GB8: Fases: | GC8: Trifásico | GJ8: Fases: | GK8: Trifásico | GO8: Fases: | GP8: Trifásico | GT8: Fases: | GU8: 1 - Monofásico | GZ8: Fases: | HA8: - | HE8: Fases: | HF8: 3 - Trifásico | HJ8: Fases: | HK8: 3 - Trifásico
E9: Potência: | F9: 224MVA | J9: Potência: | K9: 35/50MVA | O9: Potência: | P9: 37,5/53MVA | T9: Potência: | U9: 41/55MVA | Y9: Potência: | Z9: 125MVA | AD9: Potência: | AE9: 180/240/300MVA | AI9: Potência: | AJ9: 15/20/25MVA | AN9: Potência: | AO9: 15kVA | AS9: Potência: | AT9: 150MVA | AX9: Potência: | AY9: 50MVA | BC9: Potência: | BD9: 320MVA | BH9: Potência: | BI9: 25MVA | BM9: Potência: | BN9: 150MVA | BR9: Potência: | BS9: 130MVA | BW9: Potência: | BX9: 30/40/50MVA | CB9: Potência: | CC9: 90/120/150MVA | CG9: Potência: | CH9: 90/120/150MVA | CL9: Potência: | CM9: 50MVA | CQ9: Potência: | CR9: 200MVA | CV9: Potência: | CW9: 60MVAr | DA9: Óleo: | DB9: Carreta tanque - | DF9: Potência: | DG9: 18/24/30MVA | DK9: Potência: | DL9: 10/12,5 MVA | DP9: Potência: | DQ9: 40MVA | DU9: Potência: | DV9: 736 MVA | EA9: Potência: | EB9: 40 MVA | EF9: Potência: | EG9: 125 MVA | EK9: Potência: | EL9: 240 MVA | EP9: Potência: | EQ9: 150 MVA | ES9: Potência: | ET9: 150 MVA | EX9: Potência: | EY9: 15MVA | FC9: Potência: | FD9: 150MVA | FH9: Potência: | FI9: 140MVA | FM9: Potência: | FN9: 20MVA | FR9: Potência: | FS9: 300MVA | FW9: Potência: | FX9: 25MVA | GB9: Potência: | GC9: 15MVA | GJ9: Potência: | GK9: 20MVA | GO9: Potência: | GP9: 25MVA | GT9: Potência: | GU9: 66,7MVA | GZ9: Potência: | HA9: - | HE9: Potência: | HF9: 300MVA | HJ9: Potência: | HK9: 41,67MVA
E10: Tensão: | F10: 525kV | J10: Tensão: | K10: 138/13,8kV | O10: Tensão: | P10: 230/13,8kV | T10: Tensão: | U10: 69/34,5kV | Y10: Tensão: | Z10: 345kV | AD10: Tensão: | AE10: 500/138/13,8kV | AI10: Tensão: | AJ10: 138/13,8kV | AN10: Tensão: | AO10: 13,8/0,22kV | AS10: Tensão: | AT10: 230kV | AX10: Tensão: | AY10: 230/69/13,8kV | BC10: Tensão: | BD10: 500kV | BH10: Tensão: | BI10: 69kV | BM10: Tensão: | BN10: 230kV | BR10: Tensão: | BS10: 230kV | BW10: Tensão: | BX10: 138/69/13,8kV | CB10: Tensão: | CC10: 500/18kV | CG10: Tensão: | CH10: 500/18kV | CL10: Tensão: | CM10: 216kV | CQ10: Tensão: | CR10: 230kV | CV10: Tensão: | CW10: 500kV | DF10: Tensão: | DG10: 138/34,5/13,8kV | DK10: Tensão: | DL10: 138kV | DP10: Tensão: | DQ10: 138kV | DU10: Tensão: | DV10: 500/24 kV | EA10: Tensão: | EB10: 138kV | EF10: Tensão: | EG10: 345kV | EK10: Tensão: | EL10: 230 Kv | EP10: Tensão: | EQ10: 500 kV | ES10: Tensão: | ET10: 500 kV | EX10: Tensão: | EY10: 34,5 kV | FC10: Tensão: | FD10: 230kV | FH10: Tensão: | FI10: 230kV | FM10: Tensão: | FN10: 230kV | FR10: Tensão: | FS10: 230kV | FW10: Tensão: | FX10: 138kV | GB10: Tensão: | GC10: 138kV | GJ10: Tensão: | GK10: 230kV | GO10: Tensão: | GP10: 69kV | GT10: Tensão: | GU10: 550kV | GZ10: Tensão: | HA10: - | HE10: Tensão: | HF10: 525kV | HJ10: Tensão: | HK10: 138KV
E11: Óleo: | F11: - | J11: Óleo: | K11: 18.500 Litros de óleo | O11: Óleo: | P11: 17.730 Litros de óleo | T11: Óleo: | U11: 11.800 litros de óleo | Y11: Óleo: | Z11: 30.145 litros de óleo | AE11: 69.000 Litros | AJ11: 19.300 lts | AO11: sem óleo | AS11: Óleo: | AT11: 47.315 litros / Carreta Tanque | AX11: Óleo: | AY11: 40600 | BC11: Óleo: | BD11: 82.000 litros | BH11: Óleo: | BI11: litros | BM11: Óleo: | BN11: 46.760 litros | BR11: Óleo: | BS11: 39.670 litros | BW11: Óleo: | BX11: 16.300 litros | CB11: Óleo: | CC11: 21.015 litros | CG11: Óleo: | CH11: 32.300 litros | CL11: Óleo: | CM11: 21.015 litros | CQ11: Óleo: | CR11: 54.100 litros | CV11: Óleo: | CW11: 16.800 litros | DF11: Óleo: | DK11: Óleo: | DL11: 5.800 litros | DP11: Óleo: | DQ11: 17.878 Litros | DU11: Óleo: | DV11: 90.229 litros | EA11: Óleo: | EF11: Óleo: | EK11: Óleo: | EL11: 61.620 Litros | EP11: Óleo: | EQ11: 46.640 Litros | ES11: Óleo: | ET11: 46.640 Litros | EX11: Óleo: | EY11: 7.032 Litros | FC11: Óleo: | FD11: 51.420 Litros | FH11: Óleo: | FI11: 44.100 Litros | FM11: Óleo: | FN11: 14.887 Litros | FR11: Óleo: | FS11: 70.800 litros | FW11: Óleo: | FX11: 13.910 litros | GB11: Óleo: | GC11: 17.063 litros | GJ11: Óleo: | GK11: 14.887 litros | GO11: Óleo: | GP11: 10.100 litros | GT11: Local: | GU11: Gilbués / PI | GZ11: Óleo: | HA11: - | HE11: Óleo: | HF11: 77.388 lts | HJ11: Óleo: | HK11: 18.460 lts
E12: Local: | F12: Itá/SC | J12: Local: | K12: Espirito Santo | O12: Local: | P12: Vargem/SC | T12: Local: | U12: Rio do Fogo/RNN | Y12: Local: | Z12: Juiz de Fora/MG | AD12: Local: | AE12: Nova Iguaçu/RJ | AI12: Local: | AJ12: Goiânia/GO | AN12: Local: | AO12: São José dos Campos/SP | AS12: Local: | AT12: Siderópolis/SC | AX12: Local: | AY12: Nova Prata/RS | BC12: Local: | BD12: Lajes/RN | BH12: Local: | BI12: Santa Cruz/RS | BM12: Local: | BN12: Charqueadas/RS | BR12: Local: | BS12: Gentio do Ouro/BA | BW12: Local: | BX12: São Leopoldo / RS | CB12: Local: | CC12: Bahia / BA | CG12: Local: | CH12: Bahia / BA | CL12: Local: | CM12: Goiânia/GO | CQ12: Local: | CR12: Currais Novos / RN | CV12: Local: | CW12: Currau do Piaui/PI | DF12: Local: | DG12: Maringá - PR | DK12: Local: | DL12: Lençois Paulista / SP | DP12: Transp. Óleo: | DQ12: a granel | DU12: Local: | DV12: Barra dos Coqueiros / SE | EA12: Local: | EB12: São Marcos - BH | EF12: Local: | EG12: Barreiro - MG | EK12: Transp. Óleo: | EL12: a granel | EP12: Transp. Óleo: | EQ12: a granel = carreta tanque | ES12: Transp. Óleo: | EX12: Transp. Óleo: | EY12: Óleo rebaixado | FC12: Transp. Óleo: | FD12: a granel = carreta tanque | FH12: Local: | FI12: São Vicente / RN | FM12: Local: | FN12: Barreiras - BA | FR12: Local: | FS12: Jaíba / MG | FW12: Local: | FX12: Perdizes / MG | GB12: Local: | GC12: Chapada dos Guimarães / MT | GJ12: Local: | GK12: Palmas / TO | GO12: Local: | GP12: Vilhena / RO | GZ12: Local: | HA12: Itumbiara / GO | HE12: Local: | HF12: Junco do Seridó / PB | HJ12: Local: | HK12: Ponta Grossa / PR
DP13: Local: | DQ13: Cachoeira Dourada/GO | EK13: Local: | EL13: Caetite / BA | EP13: Local: | EQ13: Gurupi / TO | ES13: Local: | ET13: Gurupi / TO | EX13: Local: | EY13: Rubiataba / GO | FC13: Local: | FD13: Cascavel / PR | FH13: Dt. Prevista | FI13: 44669 | FM13: Dt. Prevista | FN13: - | FR13: Dt. Prevista | FS13: 44664 | FW13: Dt. Prevista | FX13: Imediato | GB13: Dt. Prevista | GC13: 44678 | GJ13: Dt. Prevista | GK13: - | GO13: Dt. Prevista | GP13: 44662
E14: CP: 14855688 - Comissionamento Final 07 (sete) Autotransformador Monofásico - 224MVA - 525kV - Itá/SC | J14: OF: 22010-06A CLIENTE: ARCELORMITTAL Montagem, Tratamento de óleo, Enchimentos e Comissionamento. 01 (um) Transformadores Trifásico Toshiba 35/50 MVA - 138/13,8kV - 18.500 litros de óleo isolante - Espirito Santo | O14: INSPEÇÃO RECEBIMENTO, MONTAGEM ELETROMECÂNICA, TRATAMENTO DE ÓLEO, VÁCUO, ENCHIMENTO / CIRCULAÇÃO DE ÓLEO ISOLANTE, RETOQUE DE PINTURA, COMISSIONAMENTO E ACOMPANHAMENTO START-UP 01 (UM) TRANSFORMADOR ELEVADOR TRIFÁSICO COMTRAFO – 37,5/53MVA – 230/13,8kV – 17.730 LITROS DE ÓLEO ISOLANTE - VARGEM/SC | T14: SUBSTITUIÇÃO DA BOLSA DO CONSERVADOR DO TRANSFORMADOR EQUIPAMENTOS 01 (UM) TRANSFORMADOR TRI FÁSICO 41/55 M VA 69/34,5 k V 11.800 LITROS DE ÓLEO ISOLANTE - RIO DO FOGO/RN | Y14: INSPEÇÃO DE RECEBIMENTO, MONTAGEM ELETROMECÂNICA, TRATAMENTO PARTE ATIVA, TRATAMENTO DE ÓLEO, ENCHIMENTO E COMISSIONAMENTO. 01 (UM) AUTOTRANSFORMADOR MONOFÁSICO – 125MVA – 345kV – 30.145 LITROS DE ÓLEO ISOLANTE -JUIZ DE FORA/MG | AD14: DRENAGEM DE ÓLEO, APOIO Á INSPEÇÃO INTERNA, TRATAMENTO E ENCHIMENTO DE ÓLEO. 01 (um) Transformador Monofásico - 180/240/300MVA - 500/138/13,8kV - 69.000 Litros - Nova Iguaçu/RJ | AI14: INSPEÇÃO DE RECEBIMENTO, MONTAGEM ELETROMECÂNICA, TRATAMENTO PARTE ATIVA, TRATAMENTO DE ÓLEO, ENCHIMEN TO E COMISSIONAMENTO. 01 (um) Transformador Trifásico - 15/20/25MVA - 138/13,8kV - 19.300 Litros de óleo - Goiânia/GO | AN14: OS: 180288291 CLIENTE: WEG - EDP Substituição de placa de ID,pintura de TAG do tanque e Substituição de válvulas. 02 (dois) Transformadores 15MVA - 22/13,8 kV - São José dos Campos/SP | AS14: CP: 16103116 CLIENTE: WEG - CGT ELETROSUL Inspeção,Montagem, Tratamento de óleo, Enchimentos,Comissionamento e Start-up. 02 (dois) Transformadores de Trifásicos 150 MVA - 230 kV - 47.315 litros de óleo isolante - Siderópolis/SC | AX14: Desmontagem, Remoção, Montagem Completa. 01(um) Transformador Monofásico - 50MVA - 230/69/13,8kV - 40.600 litros de óleo - Nova Prata / RS | BC14: CP: 15788638 CLIENTE: SIMM Inspeção,Montagem,Tratamento de óleo, Enchimentos e Comissionamento. 02 (dois) Transformadores Regulador Trifásicos 320 MVA - 500 kV - litros de óleo isolante - Lajes/RN | BH14: Drenagem,Desmontagem,Fornecimento de Embalagens, Remoção, Transporte, Montagem, Tratamento de óleo, Enchimentos e Comissionamento. 01 (um) Transformador Trifásicos 25 MVA - 69 kV - 15.000 litros de óleo isolante - Santa Cruz/RS | BM14: CP: 15829988 CLIENTE: WEG - MEZ ENERGIA Inspeção,Montagem, Tratamento de óleo, Enchimentos e Comissionamento. 02 (dois) Transformadores Trifásicos 150 MVA - 230 kV - 46.760 litros de óleo isolante - Charqueadas/RS | BR14: CP: 16059511 CLIENTE: WEG - OMEGA DESENV. DE ENERGIA 3 Inspeção,Montagem, Tratamento de óleo, Enchimentos,Comissionamento e Start-up. 02 (dois) Transformadores de Potência Trifásicos 130 MVA - 230 kV - 39.670 litros de óleo isolante - Gentio do Ouro/BA | BW14: OF - 21123-06A CLIENTE: RGE SUL - CPFL Montagem, Tratamento de óleo, Enchimentos e Comissionamento. 01 (um) Transformadores Trifásico TSEA 30/40/50 MVA - 138/69/13,8kV - 16.300 litros de óleo isolante - São Leopoldo/RS | CB14: OF - 21110-87 CLIENTE: UHE SÃO PILÃO ENSAIOS E MANUTENÇÃO NO TR-RESERVA E SUBSTITUIÇÃO DO TR1 PELO TR RESERVA. 02 (dois) Transformadores Elevador Trifásicos Toshiba 60/81/101,3 MVA - 138/13,8kV - 22.400 litros de óleo isolante - Apiúna / SC | CG14: CP: 15989834 - CLIENTE: WEG - CHESF DESMONTAGEM E DESCONEXÃO DE TRANSFORMADORES E RECONEXÃO DE TRANSFORMADORES NOVOS. 20 (vinte) Transformadores Monofásico - 90/120/150MVA - 500/18kV - 32.300 litros de óleo isolante - Bahia / BA | CL14: CP: 16018322 CLIENTE: WEG - CELG Inspeção de Recebimento,Montagem, Tratamento de óleo, Enchimentos,Comissionamento e Start-up. 01 (um) Autotransformador Regulador Monofásico 50MVA - 216kV - 20.800 litros a granel. Goiânia/GO | CQ14: CP: 16136137 CLIENTE: WEG Montagem, Tratamento de óleo, Enchimentos e Comissionamento. 01 (um) Transformador Monofásico 200MVA - 230kV - Currais Novos / RN | CV14: OF: 21080-07A CLIENTE: CYMIMASA Montagem, Tratamento de óleo, Enchimentos e Comissionamento. 01 (um) Reator Monofásico 60MVAr - 500kV - Currau do Piaui/PI | DF14: OF: 20080-26 CLIENTE: COPEL Montagem, Tratamento de óleo, Enchimentos e Comissionamento e SFRA. 02 (dois) Transformadores Toshiba Trifásico 18/24/30MVA - 138/34,5/13,8kV kV - Maringá-PR | DK14: CLIENTE: SENDI Serviço de enchimento e tratamento de óleo. 01 (um) Transformador Trifásico 10/12,5 MVA - 138 kV - 5.800 litros de óleo isolante. Lençois Paulista/SP | DP14: Dt. Prevista | DQ14: 44676 | DU14: CELSE Montagem, Tratamento de óleo e Comissionamento. 01 (um) Transformador Trifásico 736 MVA - 500/24 kV - 90.229 litros de óleo isolante. Barra dos Coqueiros / SE | EA14: OF: 21093-06AB/81 CLIENTE: CEMIG Montagem, Tratamento de óleo, Enchimentos e Comissionamento. 02 (dois) Transformadores Trifásico 40 MVA -138 kV (Equipamentos transp. com óleo) Belo Horizonte - MG | EF14: OF: 19162-86 CLIENTE: CEMIG Homologação, Montagem, Tratamento de óleo, Enchimentos e Comissionamento. 04 (quatro) Transformadores Monofásico 125 MVA -345 kV (Equipamentos transp. sem óleo) Belo Horizonte - MG | EK14: Dt. Prevista | EL14: 44683 | EP14: Dt. Prevista | EQ14: - | ES14: Dt. Prevista | ET14: - | EX14: Dt. Prevista | EY14: 44669 | FC14: Dt. Prevista | FD14: 44666 | GW14: SERVIÇOS:
DA15: SE BATEIAS | FH15: CP: 15671869 Cliente: SNEF-ENERG POWER Inspeção Recebimento, Montagem, Tratamento da Parte Ativa, Tratamento de Óleo, Comissionamento e Acompanhamento Start- UP 01 (um) Transformador trifásico 140MVA -230kV - 44.100 Litros de óleo (Equipamentos transp. sem óleo) - São Vicente / RN | FM15: CP: 15645876 Cliente: ENERGISA Inspeção Recebimento, Montagem, Tratamento da Parte Ativa, Tratamento de Óleo, Comissionamento e Acompanhamento Start- UP 01 (um) Reator de derivação trifásico 20MVA -230kV - 14.887 Litros de óleo (Equipamentos transp. sem óleo) - Barreiras - MG | FR15: CP: 16033870 Cliente: ABB Inspeção Recebimento, Montagem, Tratamento da Parte Ativa, Tratamento de Óleo, Comissionamento e Acompanhamento Start- UP 01 (um) Transformador Trifásico 300MVA -230kV - 70.800 Litros de óleo (Equipamentos transp. sem óleo) - Jaíba / MG | FW15: CP: 15854596 Cliente: BEM BRASIL Inspeção Recebimento, Montagem, Tratamento da Parte Ativa, Tratamento de Óleo, Comissionamento e Acompanhamento Start- UP 01 (um) Transformador Trifásico 25MVA -138kV - 13.910 Litros de óleo (Equipamentos transp. com óleo) -Perdizes / MG | GB15: CP: 16103020 | GJ15: CP:15645876 Cliente: ENERGISA - Inspeção Recebimento, Montagem, Tratamento da Parte Ativa, Tratamento de Óleo, Comissionamento e Acompa - 01 (um) Reator de Derivação Trifásico 20MVAr -230kV - 14.887 Litros de óleo (Equip. transp. sem óleo) PALMAS / TO | GO15: CP: 15127824 Cliente: ENERGISA Inspeção Recebimento, Montagem, Tratamento da Parte Ativa, Tratamento de Óleo, Comissionamento e Acompanhamento Start- UP 01 (um) Transformados Trifásico 25MVA -69kV - 10.100 Litros de óleo (Equipamentos transp. com óleo) Vilhena / RO | GW15: Desmontagem de Reator | HJ15: SRV_03922.22 - WEG_TECNOVA Inspeção Recebimento, Montagem, Tratamento da Parte Ativa, Tratamento de Óleo, Comissionamento e Acompanhamento Start- UP CP: 15772325/Cliente: TECNOVA 02 (dois) Transformadores Trifásicos 41,67MVA -138kV - 18.460 Litros de óleo (Equipamentos transp. com óleo) - Ponta Grossa / PR
DA16: 638590 | DP16: CP: 15931171 CLIENTE: FURNAS CENTRAIS ELETRICAS Inspeção Recebimento, Montagem, Tratamento da Parte Ativa, Tratamento de Óleo, Comissionamento e Acompanhamento Start- UP. 04 (quatro) Autotransformadores de Potência Monofásico 40 MVA -138 kV - 17.878 Litros de óleo (Equipamentos transp. sem óleo) Cachoeira Dourada/GO CP: 12376768 CLIENTE: FURNAS CENTRAIS ELETRICAS Desmontagem 04 (quatro) Autotransformadores Regulador Monofásico 40 MVA -138 kV - 15.400 Litros de óleo. | EK16: CP: 15928236 CLIENTE: CNS Inspeção Recebimento, Montagem, Tratamento da Parte Ativa, Tratamento de Óleo, Comissionamento e Acompanhamento Start- UP 01 (um) Transformador de Potência Trifásico 240 MVA -230 kV -61.620 Litros de óleo (Equipamentos transp. sem óleo) Caetite - BA | EP16: CP: 15645706 Cliente: ENERGISA Inspeção Recebimento, Montagem, Tratamento da Parte Ativa, Tratamento de Óleo, Comissionamento e Acompanhamento Start- UP 04 (quatro) Autotransformador Regulador Monofásico 150 MVA -500 kV -46.640 Litros de óleo (Equipamentos transp. sem óleo) 01 (um) Reator de Derivação Trifásico Gurupi - TO | EX16: CP: 15789935 Cliente: COOP RUBI Inspeção Recebimento, Montagem, Tratamento da Parte Ativa, Tratamento de Óleo, Comissionamento e Acompanhamento Start- UP. 01(um) Transformador elevador trifásico -15MVA-34,5kV-7.032 Litros de óleo (Equip. transp. com óleo rebaixado) Rubiataba - GO | FC16: CP: 14931760 Cliente: COPEL Inspeção Recebimento, Montagem, Tratamento da Parte Ativa, Tratamento de Óleo, Comissionamento e Acompanhamento Start- UP 01 (um) Autotransformador trifásico 150MVA -230kV - 51.420 Litros de óleo (Equipamentos transp. sem óleo) - Cascavel / PR | GB16: Equipamento: | GC16: Transformador | GT16: Escopo 2 | GZ16: SRV_03922.22 - WEG_TECNOVA Analises de Óleo Cliente: CARAMURU 11 (onze) Transformadores Itumbiara / GO | HE16: SRV_03920.22- PARQUE EÓLICO SERRA DO SERIDÓ VI Inspeção Recebimento, Montagem, Tratamento da Parte Ativa, Tratamento de Óleo, Comissionamento,PTA e Acompanhamento Start- UP CP: 15794488 Cliente: PARQUE EÓLICO SERRA DO SERIDÓ VI 01 (um) Transformador Trifásico 300MVA -525kV - 77.388 Litros de óleo (Equipamentos transp. sem óleo) - Junco do Seridó / PB
DA17: SE ITARARÉ | GB17: Quantidade: | GC17: 1 | GT17: Equipamento: | GU17: Reator | GW17: CP: 180283080 Cliente: NEOENERGIA Desmontagem de Reatores 01 (um) Reator Monofásico 66,67MVA -500kV - 01 (um) Reator Monofásico 100MVA -500kV Gilbués / PI
DA18: 937150 | GB18: Fases: | GC18: Trifásico | GT18: Quantidade: | GU18: 2
DA19: SE VIDEIRA | GB19: Potência: | GC19: 15MVA | GT19: Fases: | GU19: 1 - Monofásico
BH20: 2 Bombonas de 1.000 lts Tanque auxiliar 30.000 lts | DA20: 1484244 | GB20: Tensão: | GC20: 138kV | GT20: Potência: | GU20: 66,67MVA / 100MVA
DA21: SE FOZ IGUAÇU | DF21: 149048 | DK21: 87912 | GB21: Óleo: | GC21: 13.660 litros | GT21: Tensão: | GU21: 550kV / 500kV
DA22: 899220 | DU22: 295260 | EA22: 164553 | EF22: 365288 | EK22: 154480 | EP22: 574962 | ES22: 132396 | GB22: Local: | GC22: Diamantina / MT | GT22: Local: | GU22: Gilbués / PI | GZ22: 17100 | HE22: 198114 | HJ22: 0
EQ23: =SUM(EP22+ES22) -> 707358 | EX23: 86750 | FC23: 166658 | FH23: 284648 | FM23: 153186 | FR23: 207769 | FW23: 98850 | GB23: Dt. Prevista | GC23: 44662 | GJ23: 175512 | GO23: 110000 | GW23: 187000
E24: 119230 | J24: 89400 | O24: 75786 | T24: 69647 | Y24: 179800 | AD24: 83895 | AI24: 94200 | AN24: 13900 | AS24: 243546 | AX24: 0 | BC24: 421957 | BH24: 475850 | BM24: 252287 | BR24: 345254 | BW24: 96900 | CB24: 130840 | CG24: 130840 | CL24: 126800 | CQ24: 183172 | CV24: 149048 | DP24: 810578
GB25: CP: 16127767 (2X)
GB26: Equipamento: | GC26: Transformador
GB27: Quantidade: | GC27: 1
GB28: Fases: | GC28: Trifásico
GB29: Potência: | GC29: 30MVA
GB30: Tensão: | GC30: 138kV | GE30: 537120
GB31: Óleo: | GC31: 18.050 litros
GB32: Local: | GC32: Nova Mutum / MT
GB33: Dt. Prevista | GC33: 44686
GB34: Local: | GC34: Lucas do Rio Verde / MT
GB35: Dt. Prevista | GC35: 44670

Sheet CONTROLE DE PROPOSTAS ENVIADAS
C1: CONTROLE DE PROPOSTAS ENVIADAS
A2: Data | B2: Cliente | C2: Local | D2: Nº Projeto | E2: Enviado - Compras | F2: Env. - Cristiano | G2: Ret. - Cristiano | H2: Enviado ao Cliente | I2: STATUS | J2: Responsável Projeto | K2: Observação
A3: 44616 | B3: - | C3: MG | D3: SRV.03926.22 | E3: OK | F3: 44628 | G3: 44629 | H3: 44629 | I3: Env. ao cliente | J3: Mateus Delgado
A4: 44624 | B4: WEG - TECNOVA | C4: PONTA GROSSA | D4: SRV.03922.22 | E4: OK | F4: 44624 | G4: - | H4: 44627 | I4: Env. ao cliente | J4: Leonardo Locatelli | K4: ENCERRADO
A5: 44623 | B5: WEG - PARQUE EÓLICO SERRA DO SERIDÓ | C5: JUNCO SERIDO | D5: SRV.03920.22 | E5: OK | F5: 44630 | G5: 44630 | H5: 44631 | I5: Env. ao cliente | J5: Leonardo Locatelli | K5: ORÇAMENTO PERDIDO
A6: 44630 | B6: WEG - NEOENERGIA | C6: GILBUÉS/PB | D6: SRV.03933.22 | E6: OK | F6: 44631 | G6: 44635 | H6: 44635 | I6: Env. ao cliente | J6: Sara Cristina | K6: ORÇAMENTO PERDIDO
A7: 44634 | B7: WEG - ENERGISA | C7: VILHENA/TO | D7: SRV.03940.22 | E7: OK | F7: 44635 | G7: 44635 | H7: 44636 | I7: Env. ao cliente | J7: Leonardo Locatelli | K7: ORÇAMENTO PERDIDO
A8: 44634 | B8: WEG - ENERGISA | C8: PALMAS/TO | D8: SRV.03943.22 | E8: OK | F8: 44637 | G8: - | H8: 44636 | I8: Env. ao cliente | J8: Leonardo Locatelli
A9: 44636 | B9: WEG - ENERGISA - PACOTE | C9: MATO GROSSO | D9: SRV.03947.22 | E9: OK | F9: 44637 | G9: 44641 | H9: 44641 | I9: Env. ao cliente | J9: Leonardo Locatelli | K9: ORÇAMENTO PERDIDO
A10: 44637 | B10: WEG - BEM BRASIL | C10: PERDIZES/MG | D10: SRV.03953.22 | E10: OK | F10: 44637 | G10: 44641 | H10: 44641 | I10: Env. ao cliente | J10: Leonardo Locatelli
A11: 44637 | B11: WEB - ABB | C11: JAIBA/MG | D11: SRV.03954.22 | E11: OK | F11: 44641 | G11: - | H11: 44643 | I11: Env. ao cliente | J11: Leonardo Locatelli
A12: 44638 | B12: WEG - ENERGISA | C12: BARREIRAS/BA | D12: SRV.03956.22 | E12: OK | F12: - | G12: - | H12: 44642 | I12: Env. ao cliente | J12: Leonardo Locatelli | K12: ORÇAMENTO PERDIDO
A13: 44638 | B13: WEG - SNEF - ENERG POWER | C13: SÃO VICENTE/RN | D13: SRV.03960.22 | E13: OK | F13: - | G13: - | H13: 44642 | I13: Env. ao cliente | J13: Leonardo Locatelli
A14: 44641 | B14: WEG - COPEL | C14: CASCAVEL / PR | D14: SRV.03969.22 | E14: OK | F14: - | G14: - | H14: 44642 | I14: Env. ao cliente | J14: Leonardo Locatelli | K14: ORÇAMENTO PERDIDO
A15: 44641 | B15: WEG - COOP RUBI | C15: RUBIATABA / GO | D15: SRV.03974.22 | E15: OK | F15: - | G15: - | H15: 44644 | I15: Env. ao cliente | J15: Leonardo Locatelli
A16: 44642 | B16: WEG - ENERGISA | C16: GURUPI / TO | D16: SRV.03979.22 | E16: OK | F16: 44645 | G16: 44648 | H16: 44649 | I16: Env. ao cliente | J16: Leonardo Locatelli | K16: ORÇAMENTO PERDIDO
A17: 44643 | B17: WEG - COULBUN | C17: CHILE | D17: SRV.03980.22 | E17: OK | F17: - | G17: - | H17: CRISTIANO ENVIOU | I17: Env. ao cliente | J17: Lino- Chile
A18: 44644 | B18: STATE GRID | C18: ARAPORÃ / MG | D18: SRV.03985.22 | E18: OK | F18: 44645 | G18: - | H18: PRISCILA ENVIOU | I18: Env. ao cliente | J18: Ueriton
A19: 44645 | B19: MR DO BRASIL | C19: GOIANA / PE | D19: SRV.03995.22 | E19: OK | F19: 44650 | G19: - | H19: 44652 | I19: Env. ao cliente | J19: Priscils Cuchiarato
A20: 44650 | B20: TSEAS - CEMIG - BARREIRAS | C20: BELO HORIZONTE / MG | D20: SRV.04002.22 | E20: OK | F20: 44651 | H20: 44652 | I20: Env. ao cliente | J20: Matheus Souza
A21: 44650 | B21: TSEA - CEMIG - SÃO MARCOS | C21: BELO HORIZONTE / MG | D21: SRV.04003.22 | E21: OK | F21: - | H21: 44652 | I21: Env. ao cliente | J21: Matheus Souza
A22: 44650 | B22: WEG - CNS | C22: CAETITE/BA | D22: SRV.03998.22 | E22: OK | F22: 44651 | G22: 44658 | H22: 44658 | I22: Env. ao cliente | J22: Leonardo Locatelli
A23: 44652 | B23: CELSE | C23: SERGIPE / SE | D23: SRV.04010.22 | E23: OK | F23: 44652 | G23: - | H23: PRISCILA ENVIOU | I23: Env. ao cliente | J23: -
A24: 44652 | B24: ABB CHILE | C24: CHILE | D24: SRV.04012.22 | E24: OK | F24: - | G24: - | H24: CRISTIANO ENVIOU | I24: Env. ao cliente | J24: -
A25: 44655 | B25: WEG - FURNAS CENTRAIS ELETRICAS | C25: CACHOEIRA DOURADA/GO | D25: SRV.04019.22 | E25: OK | F25: 44656 | G25: 44657 | H25: 44658 | I25: Env. ao cliente | J25: Leonardo Locatelli
A26: 44659 | B26: SENDI | C26: LENÇOIS PAULISTA | D26: SRV.04032.22 | E26: OK | F26: - | G26: - | H26: 44659 | I26: Env. ao cliente | J26: Celso Junior
A27: 44664 | B27: CYMI | C27: BRÁUNA/MG | D27: SRV.04041.22 | E27: OK | F27: - | G27: - | H27: 44664 | I27: Env. ao cliente | J27: -
A28: 44669 | B28: TSEA - COPEL | C28: MARINGÁ | D28: SRV.04056.22 | E28: OK | F28: - | G28: - | H28: 44671 | I28: Env. ao cliente | J28: Matheus Souza
A29: 44671 | B29: PROLEC | C29: ATIBAIA/SP | D29: SRV.04065.22 | E29: OK | F29: - | G29: - | H29: PRISCILA ENVIOU | I29: Env. ao cliente | J29: -
A30: 44676 | B30: ENERPLAN | C30: CHILE | D30: SRV.04070.22 | E30: OK | F30: - | G30: - | H30: PRISCILA | I30: - | J30: -
A31: 44676 | B31: EVOLTZ | C31: BATEIAS | D31: SRV.04072.22 | E31: OK | F31: 44680 | G31: 44683 | H31: 44683 | I31: Env. ao cliente | J31: Igor Fernandez
A32: 44677 | B32: EVOLTZ | C32: ITARARÉ | D32: SRV.04073.22 | E32: OK | F32: 44680 | G32: 44683 | H32: 44683 | I32: Env. ao cliente | J32: Igor Fernandez
A33: 44678 | B33: EVOLTZ | C33: VIDEIRA | D33: SRV.04074.22 | E33: OK | F33: 44680 | G33: 44683 | H33: 44683 | I33: Env. ao cliente | J33: Igor Fernandez
A34: 44679 | B34: EVOLTZ | C34: FOZ DO IGUAÇU | D34: SRV.04075.22 | E34: OK | F34: 44680 | G34: 44683 | H34: 44683 | I34: Env. ao cliente | J34: Igor Fernandez
A35: 44676 | B35: TSEA - CYMIMASA | C35: CURRAU DO PIAUI/PI | D35: SRV.04078.22 | E35: OK | F35: - | G35: 44679 | H35: 44679 | I35: Env. ao cliente | J35: Matheus Souza
A36: 44677 | B36: WEG - ABB | C36: CURRAIS NOVOS/RN | D36: SRV.04080.22 | E36: OK | F36: - | G36: - | H36: 44685 | I36: Env. ao cliente | J36: Leonardo Locatelli | K36: ORÇAMENTO PERDIDO
A37: 44684 | B37: WEG - CELG | C37: GOIÂNIA/GO | D37: SRV.04094.22 | E37: OK | F37: - | G37: - | H37: 44687 | I37: Env. ao cliente | J37: Leonardo Locatelli
A38: 44683 | B38: WEG - SPIC - UHE SÃO SIMÃO | C38: GOIÂNIA/GO | D38: SRV.03907.22A | E38: OK | F38: - | G38: - | H38: 44687 | I38: Env. ao cliente | J38: Leonardo Locatelli
A39: 44683 | B39: WEG - CHESF | C39: BAHIA | D39: SRV.04098.22 | E39: - | F39: 44694 | G39: - | H39: - | J39: Leonardo Locatelli
A40: 44683 | B40: TSEA - UHE SALTO PILÃO | C40: APIÚNA/SC | D40: SRV.04100.22 | E40: OK | F40: - | G40: - | H40: 44683 | I40: Env. ao cliente | J40: Matheus Souza
A41: 44684 | B41: TSEA - RGE SUL - CPFL | C41: SÃO LEOPOLDO/RS | D41: SRV.04102.22 | E41: OK | F41: - | G41: - | H41: 44687 | I41: Env. ao cliente | J41: Leonardo Locatelli
A42: 44685 | B42: WEG - OMEGA DESENV. DE ENERGIA 3 | C42: GENTIO DO OURO/BA | D42: SRV.04105.22 | E42: OK | F42: - | G42: - | H42: 44690 | I42: Env. ao cliente | J42: Leonardo Locatelli | K42: ORÇAMENTO PERDIDO
A43: 44685 | B43: WEG - MEZ ENERGIA | C43: CHARQUEADAS/RS | D43: SRV.04106.22 | E43: OK | F43: - | G43: - | H43: 44687 | I43: Env. ao cliente | J43: Leonardo Locatelli
A44: 44685 | B44: NARI | C44: SANTA CRUZ/RS | D44: SRV.04109.22 | E44: - | F44: - | G44: - | H44: 44686 | I44: Alexandre envio Proposta | J44: Rafael
A45: 44686 | B45: WEG - SIMM | C45: LAJES/RN | D45: SRV.04114.00 | E45: OK | F45: - | G45: - | H45: 44693 | I45: Env. ao cliente | J45: Leonardo Locatelli
A46: 44687 | B46: WEG - RGE SUL - CPFL | C46: SÃO BORJA/RS | D46: SRV.04117.22 | E46: OK | F46: - | G46: - | H46: 44690 | I46: Env. ao cliente | J46: Sara Cristina
A47: 44687 | B47: PROLEC | C47: CANOAS/RS | D47: SRV.04119.22 | E47: - | J47: Graziela Oliveira
A48: 44690 | B48: CPFL | C48: NOVA PRATA/RS | D48: SRV.04120.22 | J48: Leonardo Locatelli
A49: 44691 | B49: WEG - CGT ELETROSUL | C49: SIDERÓPOLIS/SC | D49: SRV.04127.22 | E49: OK | F49: - | G49: - | H49: 44694 | I49: Env. ao cliente | J49: Leonardo Locatelli
A50: 44692 | B50: WEG - EDP SÃO PAULO | C50: SÃO JOSE DOS CAMPOS/SP | D50: SRV.04136.22 | E50: - | F50: - | G50: - | H50: 44694 | I50: Env. ao cliente | J50: Sara Cristina
A51: 44693 | B51: ENERWATT ENGENHARIA | C51: GOIANIA/GO | D51: SRV.04140.22A | E51: - | F51: - | G51: - | H51: 44694 | I51: Env. ao cliente | J51: Daniel Lima
A52: 44693 | B52: TSEA | C52: NOVA IGUAÇU/RJ | D52: SRV.04141.22 | E52: OK | F52: - | G52: - | H52: 44694 | I52: Env. ao cliente | J52: Matheus Souza
A53: 44694 | B53: WEG - CEMIG | C53: JUIZ FORA/MG | D53: SRV.04145.22 | E53: OK | F53: - | G53: -
A54: 44695 | B54: ENGELMIG | C54: RIO FOGO/RN | D54: SRV.04147.22 | E54: - | F54: - | G54: - | H54: 44697 | I54: Env. ao cliente
A55: 44697 | B55: COMTRAFO | C55: VARGEM/SC | D55: SRV.04151.22 | E55: AGD. COMPRAS | F55: - | G55: -

Sheet TOTAL DE VENDA_2026
B1: TOTAL DE VENDA 2026 — PROPOSTAS APROVADAS
B2: MÊS | C2: VALOR | D2: TOTAL ACUMULADO
B3: JAN | C3: =SUMIFS('CONTROLE DE PROPOSTAS_2026'!L:L, 'CONTROLE DE PROPOSTAS_2026'!O:O, "APROVADA", 'CONTROLE DE PROPOSTAS_2026'!P:P, ">="&DATE(2026,1,1), 'CONTROLE DE PROPOSTAS_2026'!P:P, "<="&DATE(2026,1,31)) -> 1815687.9 | D3: =IF(ROW()-2>$C$17,NA(),C3) -> 1815687.9
B4: FEV | C4: =SUMIFS('CONTROLE DE PROPOSTAS_2026'!L:L, 'CONTROLE DE PROPOSTAS_2026'!O:O, "APROVADA", 'CONTROLE DE PROPOSTAS_2026'!P:P, ">="&DATE(2026,2,1), 'CONTROLE DE PROPOSTAS_2026'!P:P, "<="&DATE(2026,2,28)) -> 2229540.9 | D4: =IF(ROW()-2>$C$17,NA(),D3+C4) -> 4045228.8
B5: MAR | C5: =SUMIFS('CONTROLE DE PROPOSTAS_2026'!L:L, 'CONTROLE DE PROPOSTAS_2026'!O:O, "APROVADA", 'CONTROLE DE PROPOSTAS_2026'!P:P, ">="&DATE(2026,3,1), 'CONTROLE DE PROPOSTAS_2026'!P:P, "<="&DATE(2026,3,31)) -> 3573121 | D5: =IF(ROW()-2>$C$17,NA(),D4+C5) -> 7618349.8
B6: ABR | C6: =SUMIFS('CONTROLE DE PROPOSTAS_2026'!L:L, 'CONTROLE DE PROPOSTAS_2026'!O:O, "APROVADA", 'CONTROLE DE PROPOSTAS_2026'!P:P, ">="&DATE(2026,4,1), 'CONTROLE DE PROPOSTAS_2026'!P:P, "<="&DATE(2026,4,30)) -> 2343121.4 | D6: =IF(ROW()-2>$C$17,NA(),D5+C6) -> 9961471.2
B7: MAI | C7: =SUMIFS('CONTROLE DE PROPOSTAS_2026'!L:L, 'CONTROLE DE PROPOSTAS_2026'!O:O, "APROVADA", 'CONTROLE DE PROPOSTAS_2026'!P:P, ">="&DATE(2026,5,1), 'CONTROLE DE PROPOSTAS_2026'!P:P, "<="&DATE(2026,5,31)) -> 988701.6 | D7: =IF(ROW()-2>$C$17,NA(),D6+C7) -> 10950173
B8: JUN | C8: =SUMIFS('CONTROLE DE PROPOSTAS_2026'!L:L, 'CONTROLE DE PROPOSTAS_2026'!O:O, "APROVADA", 'CONTROLE DE PROPOSTAS_2026'!P:P, ">="&DATE(2026,6,1), 'CONTROLE DE PROPOSTAS_2026'!P:P, "<="&DATE(2026,6,30)) -> 3116254.6 | D8: =IF(ROW()-2>$C$17,NA(),D7+C8) -> 14066427
B9: JUL | C9: =SUMIFS('CONTROLE DE PROPOSTAS_2026'!L:L, 'CONTROLE DE PROPOSTAS_2026'!O:O, "APROVADA", 'CONTROLE DE PROPOSTAS_2026'!P:P, ">="&DATE(2026,7,1), 'CONTROLE DE PROPOSTAS_2026'!P:P, "<="&DATE(2026,7,31)) -> 2135472.5 | D9: =IF(ROW()-2>$C$17,NA(),D8+C9) -> 16201900
B10: AGO | C10: =SUMIFS('CONTROLE DE PROPOSTAS_2026'!L:L, 'CONTROLE DE PROPOSTAS_2026'!O:O, "APROVADA", 'CONTROLE DE PROPOSTAS_2026'!P:P, ">="&DATE(2026,8,1), 'CONTROLE DE PROPOSTAS_2026'!P:P, "<="&DATE(2026,8,31)) -> 1180080.5 | D10: =IF(ROW()-2>$C$17,NA(),D9+C10) -> 17381980
B11: SET | C11: =SUMIFS('CONTROLE DE PROPOSTAS_2026'!L:L, 'CONTROLE DE PROPOSTAS_2026'!O:O, "APROVADA", 'CONTROLE DE PROPOSTAS_2026'!P:P, ">="&DATE(2026,9,1), 'CONTROLE DE PROPOSTAS_2026'!P:P, "<="&DATE(2026,9,30)) -> 8211239.3 | D11: =IF(ROW()-2>$C$17,NA(),D10+C11) -> 25593220
B12: OUT | C12: =SUMIFS('CONTROLE DE PROPOSTAS_2026'!L:L, 'CONTROLE DE PROPOSTAS_2026'!O:O, "APROVADA", 'CONTROLE DE PROPOSTAS_2026'!P:P, ">="&DATE(2026,10,1), 'CONTROLE DE PROPOSTAS_2026'!P:P, "<="&DATE(2026,10,31)) -> 0 | D12: =IF(ROW()-2>$C$17,NA(),D11+C12) -> #N/A
B13: NOV | C13: =SUMIFS('CONTROLE DE PROPOSTAS_2026'!L:L, 'CONTROLE DE PROPOSTAS_2026'!O:O, "APROVADA", 'CONTROLE DE PROPOSTAS_2026'!P:P, ">="&DATE(2026,11,1), 'CONTROLE DE PROPOSTAS_2026'!P:P, "<="&DATE(2026,11,30)) -> 0 | D13: =IF(ROW()-2>$C$17,NA(),D12+C13) -> #N/A
B14: DEZ | C14: =SUMIFS('CONTROLE DE PROPOSTAS_2026'!L:L,'CONTROLE DE PROPOSTAS_2026'!O:O,"APROVADA",'CONTROLE DE PROPOSTAS_2026'!P:P,">="&DATE(2026,12,1),'CONTROLE DE PROPOSTAS_2026'!P:P,"<="&DATE(2026,12,31)) -> 0 | D14: =IF(ROW()-2>$C$17,NA(),D13+C14) -> #N/A
B15: TOTAL DO ANO | C15: =SUM(C3:C14) -> 25593220
B16: Média Mensal | C16: =IFERROR(AVERAGEIF(C3:C14,">0"),0) -> 2843691.1
B17: Mês de corte (apuração) | C17: =MONTH(TODAY()) -> 9

Sheet CONTROLE DE PROPOSTAS_2024
L2: =SUBTOTAL(9,L4:L103) -> 147 | M2: =SUBTOTAL(9,M4:M103) -> 4251770 | Q2: =IFERROR(M2/L2,0) -> 28923.605
B3: QNTD. | C3: DT. ABERTURA | D3: Nº PROPOSTA | E3: CLIENTE | F3: TIPO | G3: LOCAL EXECUÇÃO | H3: DESCRIÇÃO DOS SERVIÇOS | I3: TÉCNICO | J3: DATA LIMITE | K3: DATA ENVIO | L3: PRAZO EXECUÇÃO | M3: VALOR (R$) | N3: MARGEM | O3: STATUS PROPOSTA | P3: DATA VENDA | Q3: RECEITA DIÁRIA | R3: PEDIDO UNO | S3: STATUS PEDIDO
B4: 1 | C4: 45642 | D4: P-3114 | E4: SUCOCITRICO | F4: CLIENTE FINAL | G4: CONCHAL/SP | H4: MANUTENÇÃO CORRETIVA EM 01 TRANSFORMADOR DE 13,8KV | I4: COMERCIAL | J4: 45642 | K4: 45642 | L4: 1 | M4: 22252 | N4: 0.24 | O4: EM ABERTO
B5: 2 | C5: 45643 | D5: P-3116 | E5: GRU AIRPORT | F5: CLIENTE FINAL | G5: GUARULHOS/SP | H5: FORNECIMENTO E SUBSTITUIÇÃO DE ÓLEO MINERAL ISOLANTE DE 01 TRANSFORMADOR | I5: COMERCIAL | J5: 45643 | K5: 45643 | L5: 3 | M5: 299334 | N5: 0.25 | O5: EM ABERTO
B6: 3 | C6: 45645 | D6: P-3121 | E6: ENERCAN | F6: CLIENTE FINAL | G6: CAMPOS NOVOS/SC | H6: MANUTENÇÃO CORRETIVA EM 01 TRANSFORMADOR DE 230KV | I6: COMERCIAL | J6: 45645 | K6: 45645 | L6: 20 | M6: 382100 | N6: 0.31 | O6: EM ABERTO
B7: 4 | C7: 45618 | D7: P-3086 | E7: UHE BAIXO IGUAÇU | F7: CLIENTE FINAL | G7: CAMPANEMA/PR | H7: ENSAIOS ELÉTRICOS EM 01 TRANSFORMADOR DE 230KV | I7: COMERCIAL | J7: 45618 | K7: 45618 | L7: 3 | M7: 95720 | N7: 0.27 | O7: EM ABERTO
B8: 5 | C8: 45618 | D8: P-3082 | E8: UHE BAIXO IGUAÇU | F8: CLIENTE FINAL | G8: CAMPANEMA/PR | H8: ENSAIOS DE DESCARGAS PARCIAIS EM 01 TRANSFORMADOR DE 230KV | I8: COMERCIAL | J8: 45618 | K8: 45618 | L8: 3 | M8: 494700 | N8: 0.24 | O8: EM ABERTO
B9: 6 | C9: 45614 | D9: P-3081 | E9: NEOENERGIA | F9: CLIENTE FINAL | G9: JUINA/MT | H9: ENSAIOS E SUBSTITUIÇÃO DE TPC | I9: COMERCIAL | J9: 45614 | K9: 45614 | L9: 5 | M9: 190364 | N9: 0.2 | O9: PERDIDA
B10: 7 | C10: 45582 | D10: P-3039 | E10: OMEXOM | F10: CLIENTE FINAL | G10: RIO GRANDE DO NORTE/RN | H10: MANUTENÇÃO CORRETIVA EM 01 TRANSFORMADOR | I10: COMERCIAL | J10: 45582 | K10: 45582 | L10: 7 | M10: 208750 | N10: 0.23 | O10: EM ABERTO
B11: 8 | C11: 45544 | D11: P-2987 | E11: AUREN ENERGIA | F11: CLIENTE FINAL | G11: SIMOES/PI | H11: TRATAMENTO DE ÓLEO MINERAL ISOLANTE DE 15 TRANSFORMADORES DE 34,5KV | I11: COMERCIAL | J11: 45544 | K11: 45544 | L11: 15 | M11: 149250 | N11: 0.27 | O11: EM ABERTO
B12: 9 | C12: 45463 | D12: P-2351 | E12: RIO GALEÃO | F12: CLIENTE FINAL | G12: RIO DE JANEIRO/RJ | H12: MANUTENÇÃO CORRETIVA EM TRANSFORMADORES DE AT | I12: COMERCIAL | J12: 45463 | K12: 45463 | L12: 90 | M12: 2409300 | N12: 0.27 | O12: EM ABERTO
B13: 10
B14: 11
B15: 12
B16: 13
B17: 14
B18: 15
B19: 16
B20: 17
B21: 18
B22: 19
B23: 20
B24: 21
... B58: 55
B59: 56 | Q59: =IFERROR(Tabela2252[[#This Row],[VALOR (R$)]]/Tabela2252[[#This Row],[PRAZO EXECUÇÃO]],0) -> 0
B60: 57 | Q60: =IFERROR(Tabela2252[[#This Row],[VALOR (R$)]]/Tabela2252[[#This Row],[PRAZO EXECUÇÃO]],0) -> 0
B61: 58 | Q61: =IFERROR(Tabela2252[[#This Row],[VALOR (R$)]]/Tabela2252[[#This Row],[PRAZO EXECUÇÃO]],0) -> 0
B62: 59 | Q62: =IFERROR(Tabela2252[[#This Row],[VALOR (R$)]]/Tabela2252[[#This Row],[PRAZO EXECUÇÃO]],0) -> 0
B63: 60 | Q63: =IFERROR(Tabela2252[[#This Row],[VALOR (R$)]]/Tabela2252[[#This Row],[PRAZO EXECUÇÃO]],0) -> 0
B64: 61 | Q64: =IFERROR(Tabela2252[[#This Row],[VALOR (R$)]]/Tabela2252[[#This Row],[PRAZO EXECUÇÃO]],0) -> 0
B65: 62 | Q65: =IFERROR(Tabela2252[[#This Row],[VALOR (R$)]]/Tabela2252[[#This Row],[PRAZO EXECUÇÃO]],0) -> 0
B66: 63 | Q66: =IFERROR(Tabela2252[[#This Row],[VALOR (R$)]]/Tabela2252[[#This Row],[PRAZO EXECUÇÃO]],0) -> 0
B67: 64 | Q67: =IFERROR(Tabela2252[[#This Row],[VALOR (R$)]]/Tabela2252[[#This Row],[PRAZO EXECUÇÃO]],0) -> 0
B68: 65 | Q68: =IFERROR(Tabela2252[[#This Row],[VALOR (R$)]]/Tabela2252[[#This Row],[PRAZO EXECUÇÃO]],0) -> 0
B69: 66 | Q69: =IFERROR(Tabela2252[[#This Row],[VALOR (R$)]]/Tabela2252[[#This Row],[PRAZO EXECUÇÃO]],0) -> 0
B70: 67 | Q70: =IFERROR(Tabela2252[[#This Row],[VALOR (R$)]]/Tabela2252[[#This Row],[PRAZO EXECUÇÃO]],0) -> 0
... B103: 100 | Q103: =IFERROR(Tabela2252[[#This Row],[VALOR (R$)]]/Tabela2252[[#This Row],[PRAZO EXECUÇÃO]],0) -> 0

Sheet RESUMO MENSAL
B1: MESES | C1: EM ABERTO | D1: EM NEGOCIAÇÃO | E1: PERDIDA | F1: APROVADA | G1: CANCELADA | H1: TOTAL
B2: JANEIRO | C2: =SUMIFS('CONTROLE DE PROPOSTAS_2026'!L:L, 'CONTROLE DE PROPOSTAS_2026'!O:O, "EM ABERTO", 'CONTROLE DE PROPOSTAS_2026'!B:B, ">="&DATE(2026,1,1), 'CONTROLE DE PROPOSTAS_2026'!B:B, "<="&DATE(2026,1,31)) -> 726122.1 | D2: =SUMIFS('CONTROLE DE PROPOSTAS_2026'!L:L, 'CONTROLE DE PROPOSTAS_2026'!O:O, "NEGOCIAÇÃO", 'CONTROLE DE PROPOSTAS_2026'!B:B, ">="&DATE(2026,1,1), 'CONTROLE DE PROPOSTAS_2026'!B:B, "<="&DATE(2026,1,31)) -> 300000 | E2: =SUMIFS('CONTROLE DE PROPOSTAS_2026'!L:L, 'CONTROLE DE PROPOSTAS_2026'!O:O, "PERDIDA", 'CONTROLE DE PROPOSTAS_2026'!B:B, ">="&DATE(2026,1,1), 'CONTROLE DE PROPOSTAS_2026'!B:B, "<="&DATE(2026,1,31)) -> 23521898 | F2: =SUMIFS('CONTROLE DE PROPOSTAS_2026'!L:L, 'CONTROLE DE PROPOSTAS_2026'!O:O, "APROVADA", 'CONTROLE DE PROPOSTAS_2026'!P:P, ">="&DATE(2026,1,1), 'CONTROLE DE PROPOSTAS_2026'!B:B, "<="&DATE(2026,1,31)) -> 3626365.2 | G2: =SUMIFS('CONTROLE DE PROPOSTAS_2026'!L:L, 'CONTROLE DE PROPOSTAS_2026'!O:O, "CANCELADA", 'CONTROLE DE PROPOSTAS_2026'!B:B, ">="&DATE(2026,1,1), 'CONTROLE DE PROPOSTAS_2026'!B:B, "<="&DATE(2026,1,31)) -> 0 | H2: =SUM(C2:G2) -> 28174386
B3: FEVEREIRO | C3: =SUMIFS('CONTROLE DE PROPOSTAS_2026'!L:L, 'CONTROLE DE PROPOSTAS_2026'!O:O, "EM ABERTO", 'CONTROLE DE PROPOSTAS_2026'!B:B, ">="&DATE(2026,2,1), 'CONTROLE DE PROPOSTAS_2026'!B:B, "<="&DATE(2026,2,28)) -> 449900 | D3: =SUMIFS('CONTROLE DE PROPOSTAS_2026'!L:L, 'CONTROLE DE PROPOSTAS_2026'!O:O, "NEGOCIAÇÃO", 'CONTROLE DE PROPOSTAS_2026'!B:B, ">="&DATE(2026,2,1), 'CONTROLE DE PROPOSTAS_2026'!B:B, "<="&DATE(2026,2,28)) -> 249600 | E3: =SUMIFS('CONTROLE DE PROPOSTAS_2026'!L:L, 'CONTROLE DE PROPOSTAS_2026'!O:O, "PERDIDA", 'CONTROLE DE PROPOSTAS_2026'!B:B, ">="&DATE(2026,2,1), 'CONTROLE DE PROPOSTAS_2026'!B:B, "<="&DATE(2026,2,28)) -> 6257318.7 | F3: =SUMIFS('CONTROLE DE PROPOSTAS_2026'!L:L, 'CONTROLE DE PROPOSTAS_2026'!O:O, "APROVADA", 'CONTROLE DE PROPOSTAS_2026'!P:P, ">="&DATE(2026,2,1), 'CONTROLE DE PROPOSTAS_2026'!B:B, "<="&DATE(2026,2,28)) -> 5948105.3 | G3: =SUMIFS('CONTROLE DE PROPOSTAS_2026'!L:L, 'CONTROLE DE PROPOSTAS_2026'!O:O, "CANCELADA", 'CONTROLE DE PROPOSTAS_2026'!B:B, ">="&DATE(2026,2,1), 'CONTROLE DE PROPOSTAS_2026'!B:B, "<="&DATE(2026,2,28)) -> 0 | H3: =SUM(C3:G3) -> 12904924
B4: MARÇO | C4: =SUMIFS('CONTROLE DE PROPOSTAS_2026'!L:L, 'CONTROLE DE PROPOSTAS_2026'!O:O, "EM ABERTO", 'CONTROLE DE PROPOSTAS_2026'!B:B, ">="&DATE(2026,3,1), 'CONTROLE DE PROPOSTAS_2026'!B:B, "<="&DATE(2026,3,31)) -> 5851356 | D4: =SUMIFS('CONTROLE DE PROPOSTAS_2026'!L:L, 'CONTROLE DE PROPOSTAS_2026'!O:O, "NEGOCIAÇÃO", 'CONTROLE DE PROPOSTAS_2026'!B:B, ">="&DATE(2026,3,1), 'CONTROLE DE PROPOSTAS_2026'!B:B, "<="&DATE(2026,3,31)) -> 177150 | E4: =SUMIFS('CONTROLE DE PROPOSTAS_2026'!L:L, 'CONTROLE DE PROPOSTAS_2026'!O:O, "PERDIDA", 'CONTROLE DE PROPOSTAS_2026'!B:B, ">="&DATE(2026,3,1), 'CONTROLE DE PROPOSTAS_2026'!B:B, "<="&DATE(2026,3,31)) -> 7702424.5 | F4: =SUMIFS('CONTROLE DE PROPOSTAS_2026'!L:L, 'CONTROLE DE PROPOSTAS_2026'!O:O, "APROVADA", 'CONTROLE DE PROPOSTAS_2026'!P:P, ">="&DATE(2026,3,1), 'CONTROLE DE PROPOSTAS_2026'!B:B, "<="&DATE(2026,3,31)) -> 6125031.4 | G4: =SUMIFS('CONTROLE DE PROPOSTAS_2026'!L:L, 'CONTROLE DE PROPOSTAS_2026'!O:O, "CANCELADA", 'CONTROLE DE PROPOSTAS_2026'!B:B, ">="&DATE(2026,3,1), 'CONTROLE DE PROPOSTAS_2026'!B:B, "<="&DATE(2026,3,31)) -> 475803 | H4: =SUM(C4:G4) -> 20331765
B5: ABRIL | C5: =SUMIFS('CONTROLE DE PROPOSTAS_2026'!L:L, 'CONTROLE DE PROPOSTAS_2026'!O:O, "EM ABERTO", 'CONTROLE DE PROPOSTAS_2026'!B:B, ">="&DATE(2026,4,1), 'CONTROLE DE PROPOSTAS_2026'!B:B, "<="&DATE(2026,4,30)) -> 449284 | D5: =SUMIFS('CONTROLE DE PROPOSTAS_2026'!L:L, 'CONTROLE DE PROPOSTAS_2026'!O:O, "NEGOCIAÇÃO", 'CONTROLE DE PROPOSTAS_2026'!B:B, ">="&DATE(2026,4,1), 'CONTROLE DE PROPOSTAS_2026'!B:B, "<="&DATE(2026,4,30)) -> 80690 | E5: =SUMIFS('CONTROLE DE PROPOSTAS_2026'!L:L, 'CONTROLE DE PROPOSTAS_2026'!O:O, "PERDIDA", 'CONTROLE DE PROPOSTAS_2026'!B:B, ">="&DATE(2026,4,1), 'CONTROLE DE PROPOSTAS_2026'!B:B, "<="&DATE(2026,4,30)) -> 8905623.5 | F5: =SUMIFS('CONTROLE DE PROPOSTAS_2026'!L:L, 'CONTROLE DE PROPOSTAS_2026'!O:O, "APROVADA", 'CONTROLE DE PROPOSTAS_2026'!P:P, ">="&DATE(2026,4,1), 'CONTROLE DE PROPOSTAS_2026'!B:B, "<="&DATE(2026,4,30)) -> 3753433 | G5: =SUMIFS('CONTROLE DE PROPOSTAS_2026'!L:L, 'CONTROLE DE PROPOSTAS_2026'!O:O, "CANCELADA", 'CONTROLE DE PROPOSTAS_2026'!B:B, ">="&DATE(2026,4,1), 'CONTROLE DE PROPOSTAS_2026'!B:B, "<="&DATE(2026,4,30)) -> 66160 | H5: =SUM(C5:G5) -> 13255190
B6: MAIO | C6: =SUMIFS('CONTROLE DE PROPOSTAS_2026'!L:L, 'CONTROLE DE PROPOSTAS_2026'!O:O, "EM ABERTO", 'CONTROLE DE PROPOSTAS_2026'!B:B, ">="&DATE(2026,5,1), 'CONTROLE DE PROPOSTAS_2026'!B:B, "<="&DATE(2026,5,31)) -> 16975504 | D6: =SUMIFS('CONTROLE DE PROPOSTAS_2026'!L:L, 'CONTROLE DE PROPOSTAS_2026'!O:O, "NEGOCIAÇÃO", 'CONTROLE DE PROPOSTAS_2026'!B:B, ">="&DATE(2026,5,1), 'CONTROLE DE PROPOSTAS_2026'!B:B, "<="&DATE(2026,5,31)) -> 0 | E6: =SUMIFS('CONTROLE DE PROPOSTAS_2026'!L:L, 'CONTROLE DE PROPOSTAS_2026'!O:O, "PERDIDA", 'CONTROLE DE PROPOSTAS_2026'!B:B, ">="&DATE(2026,5,1), 'CONTROLE DE PROPOSTAS_2026'!B:B, "<="&DATE(2026,5,31)) -> 9117810 | F6: =SUMIFS('CONTROLE DE PROPOSTAS_2026'!L:L, 'CONTROLE DE PROPOSTAS_2026'!O:O, "APROVADA", 'CONTROLE DE PROPOSTAS_2026'!P:P, ">="&DATE(2026,5,1), 'CONTROLE DE PROPOSTAS_2026'!B:B, "<="&DATE(2026,5,31)) -> 4264417.6 | G6: =SUMIFS('CONTROLE DE PROPOSTAS_2026'!L:L, 'CONTROLE DE PROPOSTAS_2026'!O:O, "CANCELADA", 'CONTROLE DE PROPOSTAS_2026'!B:B, ">="&DATE(2026,5,1), 'CONTROLE DE PROPOSTAS_2026'!B:B, "<="&DATE(2026,5,31)) -> 2660275 | H6: =SUM(C6:G6) -> 33018007
B7: JUNHO | C7: =SUMIFS('CONTROLE DE PROPOSTAS_2026'!L:L, 'CONTROLE DE PROPOSTAS_2026'!O:O, "EM ABERTO", 'CONTROLE DE PROPOSTAS_2026'!B:B, ">="&DATE(2026,6,1), 'CONTROLE DE PROPOSTAS_2026'!B:B, "<="&DATE(2026,6,30)) -> 3111269 | D7: =SUMIFS('CONTROLE DE PROPOSTAS_2026'!L:L, 'CONTROLE DE PROPOSTAS_2026'!O:O, "NEGOCIAÇÃO", 'CONTROLE DE PROPOSTAS_2026'!B:B, ">="&DATE(2026,6,1), 'CONTROLE DE PROPOSTAS_2026'!B:B, "<="&DATE(2026,6,30)) -> 2336345 | E7: =SUMIFS('CONTROLE DE PROPOSTAS_2026'!L:L, 'CONTROLE DE PROPOSTAS_2026'!O:O, "PERDIDA", 'CONTROLE DE PROPOSTAS_2026'!B:B, ">="&DATE(2026,6,1), 'CONTROLE DE PROPOSTAS_2026'!B:B, "<="&DATE(2026,6,30)) -> 22778750 | F7: =SUMIFS('CONTROLE DE PROPOSTAS_2026'!L:L, 'CONTROLE DE PROPOSTAS_2026'!O:O, "APROVADA", 'CONTROLE DE PROPOSTAS_2026'!P:P, ">="&DATE(2026,6,1), 'CONTROLE DE PROPOSTAS_2026'!B:B, "<="&DATE(2026,6,30)) -> 11921928 | G7: =SUMIFS('CONTROLE DE PROPOSTAS_2026'!L:L, 'CONTROLE DE PROPOSTAS_2026'!O:O, "CANCELADA", 'CONTROLE DE PROPOSTAS_2026'!B:B, ">="&DATE(2026,6,1), 'CONTROLE DE PROPOSTAS_2026'!B:B, "<="&DATE(2026,6,30)) -> 96500 | H7: =SUM(C7:G7) -> 40244791
B8: JULHO | C8: =SUMIFS('CONTROLE DE PROPOSTAS_2026'!L:L, 'CONTROLE DE PROPOSTAS_2026'!O:O, "EM ABERTO", 'CONTROLE DE PROPOSTAS_2026'!B:B, ">="&DATE(2026,7,1), 'CONTROLE DE PROPOSTAS_2026'!B:B, "<="&DATE(2026,7,31)) -> 12262269 | D8: =SUMIFS('CONTROLE DE PROPOSTAS_2026'!L:L, 'CONTROLE DE PROPOSTAS_2026'!O:O, "NEGOCIAÇÃO", 'CONTROLE DE PROPOSTAS_2026'!B:B, ">="&DATE(2026,7,1), 'CONTROLE DE PROPOSTAS_2026'!B:B, "<="&DATE(2026,7,31)) -> 192980 | E8: =SUMIFS('CONTROLE DE PROPOSTAS_2026'!L:L, 'CONTROLE DE PROPOSTAS_2026'!O:O, "PERDIDA", 'CONTROLE DE PROPOSTAS_2026'!B:B, ">="&DATE(2026,7,1), 'CONTROLE DE PROPOSTAS_2026'!B:B, "<="&DATE(2026,7,31)) -> 8613157 | F8: =SUMIFS('CONTROLE DE PROPOSTAS_2026'!L:L, 'CONTROLE DE PROPOSTAS_2026'!O:O, "APROVADA", 'CONTROLE DE PROPOSTAS_2026'!P:P, ">="&DATE(2026,7,1), 'CONTROLE DE PROPOSTAS_2026'!B:B, "<="&DATE(2026,7,31)) -> 10274807 | G8: =SUMIFS('CONTROLE DE PROPOSTAS_2026'!L:L, 'CONTROLE DE PROPOSTAS_2026'!O:O, "CANCELADA", 'CONTROLE DE PROPOSTAS_2026'!B:B, ">="&DATE(2026,7,1), 'CONTROLE DE PROPOSTAS_2026'!B:B, "<="&DATE(2026,7,31)) -> 0 | H8: =SUM(C8:G8) -> 31343213
B9: AGOSTO | C9: =SUMIFS('CONTROLE DE PROPOSTAS_2026'!L:L, 'CONTROLE DE PROPOSTAS_2026'!O:O, "EM ABERTO", 'CONTROLE DE PROPOSTAS_2026'!B:B, ">="&DATE(2026,8,1), 'CONTROLE DE PROPOSTAS_2026'!B:B, "<="&DATE(2026,8,31)) -> 13987344 | D9: =SUMIFS('CONTROLE DE PROPOSTAS_2026'!L:L, 'CONTROLE DE PROPOSTAS_2026'!O:O, "NEGOCIAÇÃO", 'CONTROLE DE PROPOSTAS_2026'!B:B, ">="&DATE(2026,8,1), 'CONTROLE DE PROPOSTAS_2026'!B:B, "<="&DATE(2026,8,31)) -> 69092 | E9: =SUMIFS('CONTROLE DE PROPOSTAS_2026'!L:L, 'CONTROLE DE PROPOSTAS_2026'!O:O, "PERDIDA", 'CONTROLE DE PROPOSTAS_2026'!B:B, ">="&DATE(2026,8,1), 'CONTROLE DE PROPOSTAS_2026'!B:B, "<="&DATE(2026,8,31)) -> 0 | F9: =SUMIFS('CONTROLE DE PROPOSTAS_2026'!L:L, 'CONTROLE DE PROPOSTAS_2026'!O:O, "APROVADA", 'CONTROLE DE PROPOSTAS_2026'!P:P, ">="&DATE(2026,8,1), 'CONTROLE DE PROPOSTAS_2026'!B:B, "<="&DATE(2026,8,31)) -> 8862319.8 | G9: =SUMIFS('CONTROLE DE PROPOSTAS_2026'!L:L, 'CONTROLE DE PROPOSTAS_2026'!O:O, "CANCELADA", 'CONTROLE DE PROPOSTAS_2026'!B:B, ">="&DATE(2026,8,1), 'CONTROLE DE PROPOSTAS_2026'!B:B, "<="&DATE(2026,8,31)) -> 0 | H9: =SUM(C9:G9) -> 22918756
B10: SETEMBRO | C10: =SUMIFS('CONTROLE DE PROPOSTAS_2026'!L:L, 'CONTROLE DE PROPOSTAS_2026'!O:O, "EM ABERTO", 'CONTROLE DE PROPOSTAS_2026'!B:B, ">="&DATE(2026,9,1), 'CONTROLE DE PROPOSTAS_2026'!B:B, "<="&DATE(2026,9,30)) -> 11238713 | D10: =SUMIFS('CONTROLE DE PROPOSTAS_2026'!L:L, 'CONTROLE DE PROPOSTAS_2026'!O:O, "NEGOCIAÇÃO", 'CONTROLE DE PROPOSTAS_2026'!B:B, ">="&DATE(2026,9,1), 'CONTROLE DE PROPOSTAS_2026'!B:B, "<="&DATE(2026,9,30)) -> 0 | E10: =SUMIFS('CONTROLE DE PROPOSTAS_2026'!L:L, 'CONTROLE DE PROPOSTAS_2026'!O:O, "PERDIDA", 'CONTROLE DE PROPOSTAS_2026'!B:B, ">="&DATE(2026,9,1), 'CONTROLE DE PROPOSTAS_2026'!B:B, "<="&DATE(2026,9,30)) -> 0 | F10: =SUMIFS('CONTROLE DE PROPOSTAS_2026'!L:L, 'CONTROLE DE PROPOSTAS_2026'!O:O, "APROVADA", 'CONTROLE DE PROPOSTAS_2026'!P:P, ">="&DATE(2026,9,1), 'CONTROLE DE PROPOSTAS_2026'!B:B, "<="&DATE(2026,9,30)) -> 8211239.3 | G10: =SUMIFS('CONTROLE DE PROPOSTAS_2026'!L:L, 'CONTROLE DE PROPOSTAS_2026'!O:O, "CANCELADA", 'CONTROLE DE PROPOSTAS_2026'!B:B, ">="&DATE(2026,9,1), 'CONTROLE DE PROPOSTAS_2026'!B:B, "<="&DATE(2026,9,30)) -> 0 | H10: =SUM(C10:G10) -> 19449952
B11: OUTUBRO | C11: =SUMIFS('CONTROLE DE PROPOSTAS_2026'!L:L, 'CONTROLE DE PROPOSTAS_2026'!O:O, "EM ABERTO", 'CONTROLE DE PROPOSTAS_2026'!B:B, ">="&DATE(2026,10,1), 'CONTROLE DE PROPOSTAS_2026'!B:B, "<="&DATE(2026,10,31)) -> 0 | D11: =SUMIFS('CONTROLE DE PROPOSTAS_2026'!L:L, 'CONTROLE DE PROPOSTAS_2026'!O:O, "NEGOCIAÇÃO", 'CONTROLE DE PROPOSTAS_2026'!B:B, ">="&DATE(2026,10,1), 'CONTROLE DE PROPOSTAS_2026'!B:B, "<="&DATE(2026,10,31)) -> 0 | E11: =SUMIFS('CONTROLE DE PROPOSTAS_2026'!L:L, 'CONTROLE DE PROPOSTAS_2026'!O:O, "PERDIDA", 'CONTROLE DE PROPOSTAS_2026'!B:B, ">="&DATE(2026,10,1), 'CONTROLE DE PROPOSTAS_2026'!B:B, "<="&DATE(2026,10,31)) -> 0 | F11: =SUMIFS('CONTROLE DE PROPOSTAS_2026'!L:L, 'CONTROLE DE PROPOSTAS_2026'!O:O, "APROVADA", 'CONTROLE DE PROPOSTAS_2026'!P:P, ">="&DATE(2026,10,1), 'CONTROLE DE PROPOSTAS_2026'!B:B, "<="&DATE(2026,10,31)) -> 0 | G11: =SUMIFS('CONTROLE DE PROPOSTAS_2026'!L:L, 'CONTROLE DE PROPOSTAS_2026'!O:O, "CANCELADA", 'CONTROLE DE PROPOSTAS_2026'!B:B, ">="&DATE(2026,10,1), 'CONTROLE DE PROPOSTAS_2026'!B:B, "<="&DATE(2026,10,31)) -> 0 | H11: =SUM(C11:G11) -> 0
B12: NOVEMBRO | C12: =SUMIFS('CONTROLE DE PROPOSTAS_2026'!L:L, 'CONTROLE DE PROPOSTAS_2026'!O:O, "EM ABERTO", 'CONTROLE DE PROPOSTAS_2026'!B:B, ">="&DATE(2026,11,1), 'CONTROLE DE PROPOSTAS_2026'!B:B, "<="&DATE(2026,11,30)) -> 0 | D12: =SUMIFS('CONTROLE DE PROPOSTAS_2026'!L:L, 'CONTROLE DE PROPOSTAS_2026'!O:O, "NEGOCIAÇÃO", 'CONTROLE DE PROPOSTAS_2026'!B:B, ">="&DATE(2026,11,1), 'CONTROLE DE PROPOSTAS_2026'!B:B, "<="&DATE(2026,11,30)) -> 0 | E12: =SUMIFS('CONTROLE DE PROPOSTAS_2026'!L:L, 'CONTROLE DE PROPOSTAS_2026'!O:O, "PERDIDA", 'CONTROLE DE PROPOSTAS_2026'!B:B, ">="&DATE(2026,11,1), 'CONTROLE DE PROPOSTAS_2026'!B:B, "<="&DATE(2026,11,30)) -> 0 | F12: =SUMIFS('CONTROLE DE PROPOSTAS_2026'!L:L, 'CONTROLE DE PROPOSTAS_2026'!O:O, "APROVADA", 'CONTROLE DE PROPOSTAS_2026'!P:P, ">="&DATE(2026,11,1), 'CONTROLE DE PROPOSTAS_2026'!B:B, "<="&DATE(2026,11,30)) -> 0 | G12: =SUMIFS('CONTROLE DE PROPOSTAS_2026'!L:L, 'CONTROLE DE PROPOSTAS_2026'!O:O, "CANCELADA", 'CONTROLE DE PROPOSTAS_2026'!B:B, ">="&DATE(2026,11,1), 'CONTROLE DE PROPOSTAS_2026'!B:B, "<="&DATE(2026,11,30)) -> 0 | H12: =SUM(C12:G12) -> 0
B13: DEZEMBRO | C13: =SUMIFS('CONTROLE DE PROPOSTAS_2026'!L:L, 'CONTROLE DE PROPOSTAS_2026'!O:O, "EM ABERTO", 'CONTROLE DE PROPOSTAS_2026'!B:B, ">="&DATE(2026,12,1), 'CONTROLE DE PROPOSTAS_2026'!B:B, "<="&DATE(2026,12,31)) -> 0 | D13: =SUMIFS('CONTROLE DE PROPOSTAS_2026'!L:L, 'CONTROLE DE PROPOSTAS_2026'!O:O, "NEGOCIAÇÃO", 'CONTROLE DE PROPOSTAS_2026'!B:B, ">="&DATE(2026,12,1), 'CONTROLE DE PROPOSTAS_2026'!B:B, "<="&DATE(2026,12,31)) -> 0 | E13: =SUMIFS('CONTROLE DE PROPOSTAS_2026'!L:L, 'CONTROLE DE PROPOSTAS_2026'!O:O, "PERDIDA", 'CONTROLE DE PROPOSTAS_2026'!B:B, ">="&DATE(2026,12,1), 'CONTROLE DE PROPOSTAS_2026'!B:B, "<="&DATE(2026,12,31)) -> 0 | F13: =SUMIFS('CONTROLE DE PROPOSTAS_2026'!L:L, 'CONTROLE DE PROPOSTAS_2026'!O:O, "APROVADA", 'CONTROLE DE PROPOSTAS_2026'!P:P, ">="&DATE(2026,12,1), 'CONTROLE DE PROPOSTAS_2026'!B:B, "<="&DATE(2026,12,31)) -> 0 | G13: =SUMIFS('CONTROLE DE PROPOSTAS_2026'!L:L, 'CONTROLE DE PROPOSTAS_2026'!O:O, "CANCELADA", 'CONTROLE DE PROPOSTAS_2026'!B:B, ">="&DATE(2026,12,1), 'CONTROLE DE PROPOSTAS_2026'!B:B, "<="&DATE(2026,12,31)) -> 0 | H13: =SUM(C13:G13) -> 0

Sheet FOLLOW-UP
A1: FOLLOW-UP
A2: Cliente | B2: Nº Proposta | C2: Serviço | D2: Local de Execução | E2: Dt. Envio Cliente | F2: Status
